Workbook

Sheet Tracker
A1: Tab | B1: Wave 0 status (Generic) | C1: Wave 1 status (Generic) | D1: Wave 3 status (Generic) | E1: Wave 4 status (DTC-IEX) | F1: Wave 5 status (EB & DG) | G1: Wave 6 status (Disability) | H1: Wave 7 status (BA & EBH) | I1: Wave 8 status (DI Claims) | J1: Wave 2 status (IM) | K1: Due Date | M1: Notes
A2: Organization Settings | B2: DONE FOR ALL
A3: Locations | B3: DONE | C3: DONE | D3: DONE for all
A4: Telephony Config | B4: DONE | C4: DONE | D4: All done unless Amelia_Hugo_1_UAT is needed | L4: Mike
A5: Users | B5: n/a | C5: DONE | D5: DONE | E5: DONE | F5: DONE | G5: DONE | H5: DONE | I5: DONE | J5: DONE | L5: Mike | M5: Tracked in alternate spreadsheet
A6: Phones Prod | B6: n/a | C6: DONE | D6: DONE | E6: DONE | F6: DONE | G6: DONE | H6: DONE | I6: DONE | J6: DONE | L6: Mike | M6: Tracked in alternate spreadsheet
A7: Custom Roles | B7: n/a | C7: DONE | D7: DONE | E7: DONE | F7: remaining custom roles will be imported with users for each wave | M7: William, James TTech, Josh from Verint / Robert GLIC
A8: DID-TFN Log | B8: DONE | C8: DONE | D8: DONE | E8: DONE | F8: DONE | G8: by go live 10/16 | H8: by go live 10/9 | I8: by go live 10/23 | J8: by go live 10/30 | K8: 45574
A9: Groups for VM - Nebula | B9: DONE FOR ALL
A10: Groups for VM - Supernova | B10: n/a | C10: DONE manually | D10: DONE | E10: DONE | F10: n/a | G10: n/a | H10: DONE | I10: DONE | J10: DONE
A11: Groups - Skill Expressions | B11: DONE | C11: DONE | D11: DONE | E11: DONE | F11: DONE | G11: DONE | H11: DONE | I11: DONE | J11: DONE
A12: External Contacts | B12: DONE FOR ALL
A13: Queues | B13: DONE | C13: DONE | D13: DONE
A14: Schedules | B14: DONE FOR ALL
A15: Schedule Groups | B15: DONE | C15: DONE | D15: DONE FOR ALL
A16: Call Routing | B16: DONE | C16: DONE 8/21
A17: Skills & Languages | B17: DONE | C17: DONE | D17: DONE | E17: DONE | F17: DONE | G17: DONE | H17: DONE | I17: DONE | J17: DONE
A18: Analytics | B18: TO BE HANDLED VIA A3S
A19: Agent Utilization | B19: DONE FOR ALL
A20: Agent Scripts | B20: n/a | C20: DONE | D20: n/a | E20: DONE | F20: n/a | G20: n/a | H20: n/a | I20: n/a | J20: n/a
A21: Status Codes | B21: DONE FOR ALL
A22: Divisions | B22: DONE FOR ALL
A23: Interaction Flows | B23: DONE | C23: DONE | D23: DONE | E23: DONE | F23: DONE | G23: DONE | H23: DONE | I23: DONE | J23: DONE | L23: Mike
A24: Flow Outcomes | B24: DONE FOR ALL
A25: Flow Milestones | B25: DONE FOR ALL
A26: ANI BLOCK LIST | B26: DONE FOR ALL
A27: Data Tables | B27: DONE | C27: DONE | D27: DONE | E27: DONE | F27: DONE | G27: DONE | H27: DONE | I27: DONE | J27: DONE
A28: Data Actions | B28: DONE | C28: DONE | D28: DONE | E28: DONE | F28: DONE | G28: DONE | H28: DONE | I28: DONE | J28: DONE | L28: Mike | M28: doing when move to prod
A29: Integrations | B29: DONE FOR ALL
A30: Recording Policy | B30: n/a | C30: DONE | D30: DONE | E30: DONE | F30: DONE | G30: Needs to be re-configured | K30: 45569 | L30: Mike | M30: has info needed
A32: UAT IT start | F32: 45530 | G32: 45538 | H32: 45530 | I32: 45544 | J32: 45551
A33: UAT Business start | F33: 45544 | G33: 45546 | H33: 45553 | I33: 45558 | J33: 45565
A34: Go live date | D34: 45539 | E34: 45546 | F34: 45560 | G34: 45581 | H34: 45574 | I34: 45588 | J34: 45595

Sheet Organization Settings
A1: Org Settings | C1: About organization settings - Genesys Cloud Resource Center (mypurecloud.com)
A2: Setting Name | B2: Description | C2: Setting
A3: Company Name | B3: Specifies the full name of your organization. Edit the Company Name to change the organization name displayed on the Login screen, on the browser tab, and on each user’s Mini Cards.
A4: Short Name | B4: Specifies the short name of your organization. Use this name to log in to the organization. You cannot edit the short name.
A5: Organization ID | B5: Specifies an ID number that is unique to each organization. A Genesys Cloud Support representative may ask for this number when troubleshooting an issue.
A6: GLOBAL SETTINGS
A7: Location Detection Available (On / Off) | B7: When ON, users' geolocation is displayed if they choose to share their current location. OFF, geolocation is disabled for everyone. | C7: On
A8: Default Language | B8: The language used for notification emails such as new user invites and password resets. | C8: English
A9: Default Country Code | B9: The default country code that is used when adding certain phone numbers. | C9: United States
A10: Issue Reporting Email Address | B10: Distribution email address for "Report an Issue" submission. Only one email address can be specified. Otherwise, emails will go to all users with "admin" role.
A11: ONBOARDING PEOPLE
A12: Auto Invite (On / Off) | B12: Send email invites automatically when users are added. | C12: off
A13: Open Admission (On / Off) | B13: People with the email domains below can add themselves to this organization. Note - disabling will invalidate your organization's sign up link. If it is re-enabled, it will create a new link. | C13: off
A14: Allowed Email Domain(s) | B14: Enter a list of domains (one per line); only people with these email domains will be allowed to sign up with this link.
A15: TELEPHONY
A16: Free Seating (On / Off) | B16: Toggle whether offline agents' assigned stations are freely available for use. | C16: off
A17: Voicemail PIN (On / Off) | B17: Toggle whether a PIN is always required for accessing voicemail, even from phones associated with the given mailbox. | C17: off
A18: Timeout Seconds | B18: The number of seconds to alert the user before the call rolls over to voicemail. | C18: 12
A19: Maximum Voicemail Length | B19: Set the maximum allowed length of a voicemail in whole minutes. | C19: 5
A20: Default TTS Engine | B20: Default TTS Engine used for flows and other cases | C20: Genesys TTS
A21: Language Overides | B21: Change TTS Engine based on interaction's language
A22: CONTACT CENTER
A23: Enforce Widget Deployments (On / Off) | B23: When on, chat is only allowed via widget deployments. When off, chats can use the legacy web chat configuration. WARNING: Only turn on this toggle after you have successfully implemented and verified widget deployments. | C23: off
A24: Strip Skills on Blind Transfer (On / Off) | B24: When on, all skills, except language(s), will be removed from the ACD interaction when blind transferred across queues. | C24: off
A25: Routing Includes Agent Presence (On / Off) | B25: When enabled, all queue routing methods will use changes in agent presence to reset the ACD routing score. This will result in interactions being delivered to the agent who has been sitting in idle/available the longest intra-day. By default, interactions are routing based on the 'time since last interaction'. | C25: off
A26: Renew Presence on Reconnect | B26: When enabled, presence status will be renewed when reconnecting to Genesys Cloud. | C26: off
A27: Enforce Communication Level After Call Work (ACW) | B27: When enabled, After Call Work ( ACW ) will be set at the communication level (vs. the participant level) to deliver better analytics and future enhancements. Additionally, supervisors will be able to utilize all queue-level ACW settings across all media types (including timeout and agent-requested options). | C27: off
A28: Route Email to multiple destinations | B28: Allow for inbound email to be routed simultaneously to multiple queues/flows based on the email addresses in the to, cc, and bcc fields. | C28: off
A29: Security & Compliance
A30: Sensitive Data Redaction for Payment Cards | B30: On a best effort basis, automatically redact Payment Card Industry (PCI) entities from recordings and transcripts. This capability is only available if speech or text analytics is enabled for the interaction. Note that users with elevated permissions can still access the original recording if needed | C30: off
A31: Sensitive Data Redaction for Personal Information | B31: On a best effort basis, automatically redact personal information entities from recordings and transcripts. This capability is only available if speech or text analytics is enabled for the interaction. Note that users with elevated permissions can still access the original recording if needed. | C31: off
A32: Disable Chat File Uploads (On / Off) | B32: When on, users cannot attach a file to the body of a chat. This setting applies to both internal chat and web chat. | C32: off
A33: Chat Message Retention Days (On / Off) | B33: The number of days, between 10 and 3650, to retain chat messages. | C33: 3650
A34: Maximum Interaction Data Retention Time | B34: Sets an organization-wide policy for the maximum retention of interaction data and recordings. The number of days after which all interactions and recordings will be deleted.
A35: HIPAA (On / Off) | B35: This setting is required for compliance with the Health Insurance Portability and Accountability Act (HIPAA | C35: off
A36: PCI DSS (On / Off) | B36: This setting is required for compliance with the Payment Card Industry Data Security Standard (PCI DSS) for handling payment cardholder data. | C36: off
A37: Voicemail Notifications | B37: Allow email notifications for Voicemail | C37: On
B38: Allow PII in Email Notifications | C38: For HIPAA compliant organizations PII will not be allowed in email notifications | D38: On
B39: Voicemail Transcription | C39: Enable Voicemail Transcriptions for your organization. | D39: Off
A40: Fax Notifications | B40: Allow email notifications for Fax | C40: On
B41: Allow PII in Email Notifications | C41: For HIPAA compliant organizations PII will not be allowed in email notifications | D41: On
A43: Restrict Genesys Cloud Embedding (On / Off) | B43: When ON, Genesys Cloud applications are restricted to where they can be embedded. OFF, Genesys Cloud applications can be embedded anywhere.
A44: Allowed Embeddable Domain(s) | B44: Enter a list of domains (one per line); only these domains will be allowed to embed Genesys Cloud applications. If no list is supplied only Genesys Cloud can embed itself.
A45: Allowed IP Addresses | B45: Enter a list of CIDRs (one per line); only requests from IP addresses within these networks will be allowed to access Genesys Cloud. If no list is supplied, all IP addresses will be allowed.
A46: Enforce Scopes | B46: When on, your organization will require approval for OAuth scopes requested by third-party applications.
A47: Division-Aware Role Management
A48: Enable Inactivity Timeout | B48: Require users to authenticate after a period of inactivity.
B49: Timeout Minutes 5 - 480 Minutes | C49: 5
A50: Role Backfill | B50: When ON, Genesys Cloud will auto-assign new permissions to default roles when new features are released. When OFF, an administrative user must manually assign new permissions to default roles to enable new features. | C50: off
A51: Pasword Requirements - Non SSO
A52: Minimum Length | C52: 12
A53: Minimum Letters | C53: 0
A54: Minimum Lower-Case Letters | C54: 1
A55: Minimum Upper-Case Letters | C55: 1
A56: Minimum Numerals | C56: 1
A57: Minimum Special Characters | C57: 1
A58: Password Expiration | C58: 90 days
A59: Minimum Age | C59: 0 days
A60: Disable GC Logon (On /Off) | B60: When ON, users will not be able to login with Genesys Cloud credentials and requires at least one single sign-on integration to be configured.
A61: Use Pop-out Authentication for Embedded Iframes | B61: Genesys Cloud embeds smaller applications utilizing iframes within the main application interface. Some of these embedded applications are required to authenticate in order to function. If using an SSO provider that does not allow authentication to take place within an iframe, set this to "ON". Otherwise, leave as "OFF". Note – setting to "ON" will require users to allow popups in their browser settings for your Genesys Cloud application domain.
A62: SSO Configuration
A63: Provider | B63: Ping Federate

Sheet Locations
A1: Location Information | J1: Add a location - Genesys Cloud Resource Center (mypurecloud.com) | K1: Address verified in org?
A2: Location Name | B2: Street Address | C2: Street Address 2 | D2: City | E2: State | F2: Zip Code | G2: Country | H2: Notes | I2: Emergency Number
A3: Bethlehem | B3: 6255 Sterners Way | D3: Bethlehem | E3: PA | F3: 18017 | G3: United States | I3: 14845101909 | J3: Wave 1 | K3: Yes
A4: Remote - NA | B4: 10 Hudson Yards 30th AVE | D4: New York | E4: NY | F4: 10001 | G4: United States | I4: 14845101905 | J4: Wave 1 | K4: Yes
A5: India BPO - Chennai | B5: #4 Rajiv Gandhi Salai | C5: #0506, D Block, Tidel Park | D5: Taramani | E5: Chennai | F5: 600113 | G5: India | H5: Not 100% sure the components are in the right column | I5: 14845101901 | K5: No
A6: India BPO - Gurgaon | B6: Candor InfoSec Tikri Sector 48 | C6: Complex Floor 7-9, Tower 1 | D6: Vill – Tikri, Sector – 48 | E6: Gurgaon | F6: 122001 | G6: India | H6: Not 100% sure the components are in the right column | I6: 14845101899 | K6: No
A7: Foundever - Philippines | B7: Benedicto St Commerce St, corner B. | D7: Cebu City, Cebu | E7: Philippines | I7: 14845101898 | K7: No
A8: Foundever - El Sal | B8: PQ5Q+5XX, Blvr. De Los Heroes, San Salvador 1101, El Salvador | I8: 14845101897 | K8: No

Sheet Telephony Config
A1: Telephony Information | I1: Number Plans
A2: Org | B2: Site Name | C2: Location | D2: Description | E2: Add. Number Plans | F2: Add. Outbound Route | G2: Built | I2: Name | J2: Match Type | K2: Match Criteria | L2: Classification | M2: Built Dev | N2: Built PROD
A3: glic-supernova | B3: Bethlehem | C3: Bethlehem | E3: Hugo Prod, BYOC | F3: Hugo Prod, BYOC | G3: Yes | H3: Needs BYOC Route, default route | I3: Hugo Dev | J3: e.164 Number List | K3: +16101951100 - 1104 | L3: Hugo Dev | M3: N/A | N3: N/A | O3: (n/a becuse tracked on site progress)
B4: Holmdel | C4: Holmdel | E4: Hugo Prod, BYOC | F4: Hugo Prod, BYOC | G4: Yes | H4: Needs BYOC Route, default route | I4: Hugo UAT | J4: e.164 Number List | K4: +16101952100 - 2104 | L4: Hugo UAT | M4: N/A | N4: N/A
B5: Hudson Yards | C5: Hudson Yards | E5: Hugo Prod, BYOC | F5: Hugo Prod, BYOC | G5: Yes | H5: Needs BYOC Route, default route | I5: Hugo Prod | J5: e.164 Number List | K5: +16101953100 - 3104 | L5: Hugo Prod | M5: N/A | N5: N/A
B6: Pittsfield | C6: Pittsfield | E6: Hugo Prod, BYOC | F6: Hugo Prod, BYOC | G6: Yes | H6: Needs BYOC Route, default route | I6: BYOC | J6: e.164 Number List | K6: +16101990000 - 9999 | L6: BYOC | M6: N/A | N6: N/A
B7: India BPO - Chennai | C7: India BPO - Chennai | E7: Hugo Prod, BYOC | F7: Hugo Prod, BYOC | G7: Yes | H7: Needs BYOC Route, default route | I7: Outbound Routes
B8: India BPO - Gurgaon | C8: India BPO - Gurgaon | E8: Hugo Prod, BYOC | F8: Hugo Prod, BYOC | G8: Yes | H8: Needs BYOC Route, default route | I8: Name
B9: Foundever - Philippines | C9: Foundever - Philippines | E9: Hugo Prod, BYOC | F9: Hugo Prod, BYOC | G9: Yes | H9: Needs BYOC Route
B10: Foundever - El Sal | C10: Foundever - El Sal | E10: Hugo Prod, BYOC | F10: Hugo Prod, BYOC | G10: Yes | H10: Needs BYOC Route
B11: Remote - NA | C11: Remote - NA | E11: Hugo Prod, BYOC | F11: Hugo Prod, BYOC | G11: Yes | H11: Needs Hugo route, default route
A12: glic-nebula | B12: Testing Site | C12: Testing Location | E12: Hugo Dev, Hugo UAT | F12: Hugo DEV, Hugo UAT | G12: Yes
B13: PureCloud Voice - AWS | C13: Default PCV Location | E13: Hugo Dev, Hugo UAT | F13: Hugo DEV, Hugo UAT | G13: Yes
A17: Org | B17: Base Phone Settings | C17: Relevent Information | F17: Built DEV | G17: Built Prod
A18: All | B18: WebRTC Base | F18: Yes | G18: Yes
A23: Org | B23: Trunk Config | C23: Type | D23: Enable SIP REFER | E23: Protocol | F23: Inbound - Number Plan Site | G23: Inbound - SIP Term ID | H23: Outbound - SIP Term ID | I23: SIP Servers or Proxies | J23: Caller ID # and Name | K23: Caller ID Prioritization | L23: Suppress User | M23: SIP Access Control | N23: Recording | O23: Additional Notes | P23: Built
A24: glic-supernova | B24: GDDOVSBCAPPP | C24: BYOC Generic Carrier | D24: FALSE | E24: TLS | G24: gdd-supernova.glic | H24: DDC-GenesysCloudCX1.glic.com | I24: 209.10.184.8:5061 | K24: Call Source/Site/Trunk | L24: Always | M24: 209.10.184.8 | N24: On | P24: Yes
B25: GRDOVSBCAPPP | C25: BYOC Generic Carrier | D25: FALSE | E25: TLS | G25: grd-supernova.glic | H25: DDC-GenesysCloudCX3.glic.com | I25: 209.10.184.9:5061 | K25: Call Source/Site/Trunk | L25: Always | M25: 209.10.184.9 | N25: On | P25: Yes
B26: Amelia_Hugo_1 | C26: BYOC Generic Carrier | D26: TRUE | E26: TLS | G26: use1-prod-sbc-25 | H26: use1-prod-sbc-25.sip.amelia.com | I26: use1-prod-sbc-25.sip.amelia.com:5062 | K26: Trunk | L26: Always | M26: 54.242.117.115 | N26: On | P26: Yes
B27: Amelia_Hugo_2 | C27: BYOC Generic Carrier | D27: TRUE | E27: TLS | G27: use1-prod-sbc-26 | H27: use1-prod-sbc-26.sip.amelia.com | I27: use1-prod-sbc-26.sip.amelia.com:5062 | K27: Trunk | L27: Always | M27: 3.218.217.246 | N27: On | P27: Yes
B28: Amelia_Hugo_3 | C28: BYOC Generic Carrier | D28: TRUE | E28: TLS | G28: use2-prod-sbc-25 | H28: use2-prod-sbc-25.sip.amelia.com | I28: use2-prod-sbc-25.sip.amelia.com:5062 | K28: Trunk | L28: Always | M28: 18.190.30.8 | N28: On | P28: Yes
B29: Amelia_Hugo_4 | C29: BYOC Generic Carrier | D29: TRUE | E29: TLS | G29: use2-prod-sbc-26 | H29: use2-prod-sbc-26.sip.amelia.com | I29: use2-prod-sbc-26.sip.amelia.com:5062 | K29: Trunk | L29: Always | M29: 3.17.114.33 | N29: On | P29: Yes
B30: PureCloud Voice - AWS | C30: Genesys Cloud Voice | D30: FALSE | K30: Call Source/Site/Trunk | L30: Always | N30: On | P30: Yes
A31: DR | B31: Dallas | C31: BYOC Generic Carrier | D31: FALSE | E31: TLS | G31: Guardian_DR_Dallas | K31: Call Source/Site/Trunk | L31: Always | N31: On | P31: No
B32: Richmond | C32: BYOC Generic Carrier | D32: FALSE | E32: TLS | G32: Guardian_DR_Richmond | K32: Call Source/Site/Trunk | L32: Always | N32: On | P32: No
B33: Amelia_Hugo_1 | C33: BYOC Generic Carrier | D33: TRUE | E33: TLS | G33: use1-prod-sbc-25 | H33: use1-prod-sbc-25.sip.amelia.com | I33: use1-prod-sbc-25.sip.amelia.com:5062 | K33: Trunk | L33: Always | M33: 54.242.117.115 | N33: On | P33: No
B34: Amelia_Hugo_2 | C34: BYOC Generic Carrier | D34: TRUE | E34: TLS | G34: use1-prod-sbc-26 | H34: use1-prod-sbc-26.sip.amelia.com | I34: use1-prod-sbc-26.sip.amelia.com:5062 | K34: Trunk | L34: Always | M34: 3.218.217.246 | N34: On | P34: No
B35: Amelia_Hugo_3 | C35: BYOC Generic Carrier | D35: TRUE | E35: TLS | G35: use2-prod-sbc-25 | H35: use2-prod-sbc-25.sip.amelia.com | I35: use2-prod-sbc-25.sip.amelia.com:5062 | K35: Trunk | L35: Always | M35: 18.190.30.8 | N35: On | P35: No
B36: Amelia_Hugo_4 | C36: BYOC Generic Carrier | D36: TRUE | E36: TLS | G36: use2-prod-sbc-26 | H36: use2-prod-sbc-26.sip.amelia.com | I36: use2-prod-sbc-26.sip.amelia.com:5062 | K36: Trunk | L36: Always | M36: 3.17.114.33 | N36: On | P36: No
B37: PureCloud Voice - AWS | C37: Genesys Cloud Voice | D37: FALSE | K37: Call Source/Site/Trunk | L37: Always | N37: On | P37: No
A38: glic-nebula | B38: GDDOVSBCAPPQ | C38: BYOC Generic Carrier | D38: FALSE | E38: TLS | G38: gdd-nebula.glic | H38: DDC-GenesysCloudCX2.glic.com | I38: 209.10.184.31:5061 | K38: Call Source/Site/Trunk | L38: Always | M38: 209.10.184.31 | N38: On | P38: Yes
B39: GRDOVSBCAPPQ | C39: BYOC Generic Carrier | D39: FALSE | E39: TLS | G39: Guardian_DEV_Richmond | H39: DDC-GenesysCloudCX4.glic.com | I39: 209.10.184.32:5061 | K39: Call Source/Site/Trunk | L39: Always | M39: 209.10.184.32 | N39: On | P39: Yes
B40: Amelia_Hugo_1_UAT | C40: BYOC Generic Carrier | D40: TRUE | E40: TLS | K40: Trunk | L40: Always | P40: No
B41: Amelia_Hugo_1_DEV | C41: BYOC Generic Carrier | D41: TRUE | E41: TLS | G41: use2-dev-sbc-25 | H41: use2-dev-sbc-25.sip.amelia.com | I41: use2-dev-sbc-25.sip.amelia.com:5062 | K41: Trunk | L41: Always | M41: 3.12.191.10 | N41: On | P41: Yes
B42: PureCloud Voice - AWS | C42: Genesys Cloud Voice | D42: FALSE | L42: Always | N42: On | P42: Yes
A44: Org | B44: Edge Size | C44: Edge Count | D44: Notes
A45: glic-supernova/DR | B45: r4.xlarge | C45: 2
A46: glic-nebula | B46: t3a.medium | C46: 2
A52: About telephony - Genesys Cloud Resource Center (mypurecloud.com)

Sheet Users
A1: name | B1: email | C1: phone_work | D1: extension | E1: title | F1: department | G1: email_manager | H1: location_work | I1: roles_divisions | J1: queues | K1: division | L1: skills | M1: enable auto_answer
A2: FirstName LastName | B2: Agent@email.com | C2: 15555555555 | D2: 1234 | E2: Agent | F2: Contact Center | G2: manager@email.com | H2: Reston, VA | I2: role a [division 1; division 2], role b [division 1], User [division 1; division 2], role b [division 1] | J2: Queue1, Queue2 | K2: Global | L2: ExampleSkill1:3
A5: Tracked in alternate spreadsheet

Sheet Phones Prod
A1: name | B1: base | C1: site | D1: email | E1: remoteAddress | F1: hardwareId | G1: keyLabel | H1: lineAppearanceId | I1: did | J1: extension | K1: Built | R1: Import phones - Genesys Cloud Resource Center (mypurecloud.com) | W1: Roles
A2: Conference Room 2 | B2: Polycom Trio 8800 BaseSettings | C2: Main Office | F2: xxxxxxxxxxxx | I2: 3172222222 | J2: 2222 | W2: Communicate - User
A3: Jon Doe WebRTC | B3: WebRTC Base Settings | C3: Main Office | D3: jon.doe@customer.com | W3: User
W4: Supervisor
W5: Quality Administrator
W6: Quality Evaluator
W7: WFM Admin
A8: Tracked in alternate spreadsheet | W8: SOA PAX Reporting

Sheet Phones Dev
A1: name | B1: base | C1: site | D1: email | E1: remoteAddress | F1: hardwareId | G1: keyLabel | H1: lineAppearanceId | I1: did | J1: extension | K1: Built | R1: Import phones - Genesys Cloud Resource Center (mypurecloud.com) | W1: Roles
A2: Conference Room 2 | B2: Polycom Trio 8800 BaseSettings | C2: Main Office | F2: xxxxxxxxxxxx | I2: 3172222222 | J2: 2222 | W2: Communicate - User
A3: Jon Doe WebRTC | B3: WebRTC Base Settings | C3: Main Office | D3: jon.doe@customer.com | W3: User
W4: Supervisor
W5: Quality Administrator
W6: Quality Evaluator
W7: WFM Admin
W8: SOA PAX Reporting

Sheet Role Modifications
A1: Role Modifications
A2: Role Name | B2: Description | C2: Permission modifications | D2: Built Prod | E2: Built Dev | F2: Roles and permissions overview - Genesys Cloud Resource Center (mypurecloud.com)
A3: employee
A4: Communicate - User
A5: User | C5: Remove ability to join/unjoin queues Remove ability to pause recording Remove ability to adhoc record calls
A6: Supervisor
A7: Communicate - Admin
A8: admin
A9: Master Admin
A10: Telephony Admin
A11: Developer
A12: Quality Evaluator | C12: Add ability to assign evaluations to interactions
A13: Quality Administrator
A14: Planner Admin
A15: Script Designer
A16: Genesys Cloud Voice Admin
A17: Performance Management Admin

Sheet Custom Roles
A1: Custom Role Name | B1: Description | C1: Permissions Included | D1: Built Prod | E1: Built Dev | F1: Notes / updates | H1: Products, roles, and permissions list - Genesys Cloud Resource Center (mypurecloud.com)
A2: Agent | C2: Architect / flow / Edit Architect / flow / Publish Architect / flow / View Architect / systemPrompt / All Permissions Architect / ui / View Architect / userPrompt / All Permissions authorization / grant / All Permissions authorization / role / View Directory > User > All Permissions General / Role Manager General / User Administration General / User Manager Routing / Wrap-up Codes / All Permissions Telephony / Plugin / All | D2: Yes | E2: Yes
A3: Leader | C3: Architect > All Permissions Bridge > Actions > All Permissions Directory > Group > All Permissions Directory > User > All Permissions Directory > userPassword > All Permissions externalContacts > All Permissions General > Person Administration General > Role Manager General > User Manager integrations > All Permissions Recording > All Permissions Routing > All Permissions Single Sign-on All Permissions | D3: Yes | E3: Yes
A4: WFM | D4: Yes | E4: Yes
A5: QM | D5: Yes | E5: Yes
A6: Reviewer | D6: Yes | E6: Yes
A7: Voicemail | C7: user > voicemail > Transfer Voicemail > ACD Voicemail > Delete Voicemail > ACD Voicemail > View Voicemail > Voicemail > Receive | D7: Yes | E7: Yes
A8: Agent WFM | B8: allows TTEC adapter to track > Verint | C8: integration > ariaWFMApps > view | D8: Yes | E8: Yes | F8: 8/20 Brenda: Robert confirmed via email that this role is needed w/permission provided (permission only applies to this new role)
F9: 8/27 Robert - Agents who need this role -- Wave 4: GLIC Retail, Foundever Retail Wave 5: GLIC Dental, Foundever Dental Wave 6: GLIC Group DI, Foundever Group DI Wave 7: NSC Wave 8: IM Claims Wave 2: IMCC

Sheet DID-TFN Log
B1: (Assign to Pre-IVR Call Route) | C1: (Assign to Flow's Call Route)
A2: Flow | B2: TFN(s) | C2: Dummy DID A | D2: Dummy DID B
A3: Individual Markets IVR | B3: +18004416455, +18008192468, +18002213253, +18885003467, +18003507314 | C3: 15551110002 | D3: 15552220002
A4: Individual Markets - Claimant IVR | B4: +18664524542 | C4: 15551110011 | D4: 15552220011
A5: Individual Markets - PAS IVR | B5: +18886000003, +18886004667 | C5: 15551110012 | D5: 15552220012
A6: Individual Markets - PAIA IVR | C6: 15551110013 | D6: 15552220013
A7: Dental IVR | C7: 15551110006 | D7: 15552220006
A8: Direct to Consumer IEX IVR | B8: +18666599900, +18445615600, +18882434578 | C8: 15551110003 | D8: 15552220003
A9: Employee Benefits IVR | C9: 15551110005 | D9: 15552220005
A10: Employee Benefits Hotline IVR | C10: 15551110007 | D10: 15552220007
A11: HB Recuritment IVR | C11: 15551110010 | D11: 15552220010
A12: Generic Menu IVR | C12: 15551110000 | D12: 15552220000
A13: Password Reset IVR | B13: +18664409326, +18664408924 | C13: 15551110001 | D13: 15552220001
A14: Group Disability IVR | C14: 15551110004 | D14: 15552220004
A15: Broker Admin IVR | C15: 15551110008 | D15: 15552220008
A16: postivr_routing | B16: N/A | C16: 15551110009 | D16: 15552220009
A18: DID Range Purpose | B18: DID Range | C18: Built Prod | D18: Built Dev
A19: Dummy DID A | B19: +15551110000 - +15551110099 | C19: Yes | D19: Yes
A20: Dummy DID B | B20: +15552220000 - +15552220099 | C20: Yes | D20: Yes
A21: In Use TFNs | B21: Many/discontiguous (~130) | C21: No | D21: No | E21: see Go live tracker - configured night of go live
A22: Out of Use TFNs | B22: Many/discontiguous (~470) | C22: No | D22: No | E22: see Go live tracker - configured night of go live
A23: Transfer numbers | B23: Many/discontiguous 1610199xxxx | C23: No | D23: No | E23: see Go live tracker - configured night of go live
A25: Extension Range Purpose | B25: Extension Range | C25: Built Prod | D25: Built Dev
A26: External inbound to users | B26: Get from user sheet
A27: Group for Voicemail | B27: 8000-8999 | C27: Yes | D27: Yes
A28: User extensions | B28: 30000-30500 | C28: Yes | D28: N/A
A32: Manage DID and toll-free number ranges - Genesys Cloud Resource Center (mypurecloud.com)
A33: Manage DID and toll-free number assignments - Genesys Cloud Resource Center (mypurecloud.com)

Sheet Groups
A1: Group Config | D1: About groups - Genesys Cloud Resource Center (mypurecloud.com)
A2: Group Name | B2: Admin Team | D2: About setting up groups (admins) - Genesys Cloud Resource Center (mypurecloud.com)
A3: Type | B3: Official / Social
A4: Visibility Public: Anyone can find the group. Members Only: Only members of the group can find the group. Owners Only: Only owners and members of the group can find the group. | B4: Members Only / Owners Only / Public
A5: Include Owners | B5: yes / no
A6: Enable Calls | B6: On / Off
A7: Group Phone Number / Extension | B7: <DID number in E164 format> <Extension configured on the platform>
A8: Call Route Type Broadcast: 15 randomly selected members will be called simultaneously with a maximum of 1,000 members in rotation. Sequential: Sequential routes will call members in a specified order. Rotary: Rotary routes will call members based on who has last received a call. | B8: Broadcast / Sequential / Rotary
A9: Rotate Calls | B9: Every T seconds | C9: T =
A10: Stop Ringing | B10: After N rotations | C10: N =
A11: Overflow | B11: Off / On
A12: Overflow / Back-up Contact Note: Overflow calls will always be broadcast.
A13: Voicemail | B13: Off / On
A14: Voicemail / Greeting | B14: No audio selected or recorded / <Wav file name>
A15: Voicemail / Email Notification | B15: Off On (Send email notification to members for group voicemails)
A16: Members | B16: <User 1> | C16: Ext:
B17: <User 2> | C17: Ext:
B18: <User 3> | C18: Ext:
B19: <User 4> | C19: Ext:
B20: <User 5> | C20: Ext:
A21: Owners | B21: <User 1>
B22: <User 2>
B23: <User 3>
B24: <User 4>
B25: <User 5>

Sheet Groups for VM - Nebula
A1: Group Config | B1: About Groups - Genesys Cloud Resource Center (mypurecloud.com)
B2: About setting up Groups (admins) - Genesys Cloud Resource Center (mypurecloud.com)
A3: Group Name | B3: Type | C3: Visibility | D3: Include owners | E3: Enable Calls | F3: Group Phone Number / Extension | G3: Call Route Type | H3: Rotate Calls | I3: Stop Ringing | J3: Overflow | K3: Overflow / Back-up Contact | L3: Voicemail | M3: Voicemail / Greeting | N3: Voicemail / Email Notification | O3: Members | P3: Owners
A4: Broker_VM_Opt_Greater_Atlanta_DN_Group | B4: Official | C4: Public | D4: yes | E4: yes | F4: 8000 | G4: Rotary | H4: 12 | I4: 10 | J4: no | L4: yes | P4: Pooja Konda, Anirban Chakravarty, Simonti Sen,QA users
A5: Broker_VM_Opt_Greater_Chicago_DN_Group | B5: Official | C5: Public | D5: yes | E5: yes | F5: 8001 | G5: Rotary | H5: 12 | I5: 10 | J5: no | L5: yes | P5: Pooja Konda, Anirban Chakravarty, Simonti Sen,QA users
A6: Broker_VM_Opt_Pennsylvania_DN_Group | B6: Official | C6: Public | D6: yes | E6: yes | F6: 8002 | G6: Rotary | H6: 12 | I6: 10 | J6: no | L6: yes | P6: Pooja Konda, Anirban Chakravarty, Simonti Sen,QA users
A7: Team_Smith_Gusto_OF_Group | B7: Official | C7: Public | D7: yes | E7: yes | F7: 8003 | G7: Rotary | H7: 12 | I7: 10 | J7: no | L7: yes | P7: Pooja Konda, Anirban Chakravarty, Simonti Sen,QA users
A8: Broker_VM_Opt_Texas_DN_Group | B8: Official | C8: Public | D8: yes | E8: yes | F8: 8004 | G8: Rotary | H8: 12 | I8: 10 | J8: no | L8: yes | P8: Pooja Konda, Anirban Chakravarty, Simonti Sen,QA users
A9: Team_Jefferies_OF_Group | B9: Official | C9: Public | D9: yes | E9: yes | F9: 8005 | G9: Rotary | H9: 12 | I9: 10 | J9: no | L9: yes | P9: Pooja Konda, Anirban Chakravarty, Simonti Sen,QA users
A10: Broker_VM_Opt_No_Cal_DN_Group | B10: Official | C10: Public | D10: yes | E10: yes | F10: 8006 | G10: Rotary | H10: 12 | I10: 10 | J10: no | L10: yes | P10: Pooja Konda, Anirban Chakravarty, Simonti Sen,QA users
A11: Team_Smith_OF_Group | B11: Official | C11: Public | D11: yes | E11: yes | F11: 8007 | G11: Rotary | H11: 12 | I11: 10 | J11: no | L11: yes | P11: Pooja Konda, Anirban Chakravarty, Simonti Sen,QA users
A12: Broker_VM_Opt_Florida_DN_Group | B12: Official | C12: Public | D12: yes | E12: yes | F12: 8008 | G12: Rotary | H12: 12 | I12: 10 | J12: no | L12: yes | P12: Pooja Konda, Anirban Chakravarty, Simonti Sen,QA users
A13: Team_Kober_OF_Group | B13: Official | C13: Public | D13: yes | E13: yes | F13: 8009 | G13: Rotary | H13: 12 | I13: 10 | J13: no | L13: yes | P13: Pooja Konda, Anirban Chakravarty, Simonti Sen,QA users
A14: Broker_VM_Opt_Greater_New_York_DN_Group | B14: Official | C14: Public | D14: yes | E14: yes | F14: 8010 | G14: Rotary | H14: 12 | I14: 10 | J14: no | L14: yes | P14: Pooja Konda, Anirban Chakravarty, Simonti Sen,QA users
A15: Broker_VM_Opt_Great_Lakes_DN_Group | B15: Official | C15: Public | D15: yes | E15: yes | F15: 8011 | G15: Rotary | H15: 12 | I15: 10 | J15: no | L15: yes | P15: Pooja Konda, Anirban Chakravarty, Simonti Sen,QA users
... A202: Broker_VM_Opt_Broker_Sequoia_OF_Group | B202: Official | C202: Public | D202: yes | E202: yes | F202: 8198 | G202: Rotary | H202: 12 | I202: 10 | J202: no | L202: yes | P202: Pooja Konda, Anirban Chakravarty, Simonti Sen,QA users

Sheet Groups for VM - Supernova
A1: Group Config | B1: About Groups - Genesys Cloud Resource Center (mypurecloud.com)
B2: About setting up Groups (admins) - Genesys Cloud Resource Center (mypurecloud.com)
A3: Group Name | B3: Type | C3: Visibility | D3: Include owners | E3: Enable Calls | F3: Group Phone Number / Extension | G3: Call Route Type | H3: Rotate Calls | I3: Stop Ringing | J3: Overflow | K3: Overflow / Back-up Contact | L3: Voicemail | M3: Voicemail / Greeting | N3: Voicemail / Email Notification | O3: Members | P3: Owners
A4: Broker_VM_Opt_Greater_Atlanta_DN_Group | B4: Official | C4: Public | D4: yes | E4: yes | F4: 8000 | G4: Rotary | H4: 12 | I4: 10 | J4: no | L4: yes | O4: caroline_ferguson@glic.com,Erin_Ziegert@glic.com,rachel_gustave@glic.com,whitnee_steger@glic.com,amber_brittian@glic.com,seindhy_piquion@glic.com | P4: Pooja Konda, Anirban Chakravarty, Simonti Sen, Garrett Napier, Dan Wolf, Robert J. Paxton
A5: Broker_VM_Opt_Greater_Chicago_DN_Group | B5: Official | C5: Public | D5: yes | E5: yes | F5: 8001 | G5: Rotary | H5: 12 | I5: 10 | J5: no | L5: yes | O5: darian_briemann@glic.com,rachael_evers@glic.com,agatha_gallion@glic.com | P5: Pooja Konda, Anirban Chakravarty, Simonti Sen, Garrett Napier, Dan Wolf, Robert J. Paxton
A6: Broker_VM_Opt_Pennsylvania_DN_Group | B6: Official | C6: Public | D6: yes | E6: yes | F6: 8002 | G6: Rotary | H6: 12 | I6: 10 | J6: no | L6: yes | O6: teri_klarner@glic.com,Dana_VanNatten@glic.com,lamika_mcnichols@glic.com,Susan_Morrow@glic.com | P6: Pooja Konda, Anirban Chakravarty, Simonti Sen, Garrett Napier, Dan Wolf, Robert J. Paxton
A7: Team_Smith_Gusto_OF_Group | B7: Official | C7: Public | D7: yes | E7: yes | F7: 8003 | G7: Rotary | H7: 12 | I7: 10 | J7: no | L7: yes | O7: josey_wendler@glic.com,karen_hietpas@glic.com,amy_nyce@glic.com,catherine_malitsis@glic.com,angela_louros@glic.com,Jennifer_VanHandel@glic.com | P7: Pooja Konda, Anirban Chakravarty, Simonti Sen, Garrett Napier, Dan Wolf, Robert J. Paxton
A8: Broker_VM_Opt_Texas_DN_Group | B8: Official | C8: Public | D8: yes | E8: yes | F8: 8004 | G8: Rotary | H8: 12 | I8: 10 | J8: no | L8: yes | O8: teri_wussow@glic.com,cassidy_beahn@glic.com,quinnetta_crayton@glic.com,patricia_rollberg@glic.com,christine_eder@glic.com,Nicholas_Rossi-Marino@glic.com,Amanda_Matczak@glic.com | P8: Pooja Konda, Anirban Chakravarty, Simonti Sen, Garrett Napier, Dan Wolf, Robert J. Paxton
A9: Team_Jefferies_OF_Group | B9: Official | C9: Public | D9: yes | E9: yes | F9: 8005 | G9: Rotary | H9: 12 | I9: 10 | J9: no | L9: yes | O9: Amy_Hietpas@glic.com,asha_cull@glic.com,ashley_natali@glic.com,bethann_bogucki@glic.com,Brian_Rusch@glic.com,Mary-Jane_Lower@glic.com,Shelley_Zeegers@glic.com,Stephanie_werley@glic.com,elizabeth_wapinski@glic.com,kathy_wilson@glic.com,Alyssa_Reed@glic.com,amber_richardson@glic.com,crystal_mathews@glic.com,Deborah_A_Berger@glic.com,Milagros_Jordan@glic.com,taylor_x_johnson@glic.com | P9: Pooja Konda, Anirban Chakravarty, Simonti Sen, Garrett Napier, Dan Wolf, Robert J. Paxton
A10: Broker_VM_Opt_No_Cal_DN_Group | B10: Official | C10: Public | D10: yes | E10: yes | F10: 8006 | G10: Rotary | H10: 12 | I10: 10 | J10: no | L10: yes | O10: chris_bucklin@glic.com,crystal_sjoquist@glic.com,tempestt_dubose@glic.com,Cari_Taylor@glic.com,Candice_Guehrn@glic.com,amber_rice@glic.com | P10: Pooja Konda, Anirban Chakravarty, Simonti Sen, Garrett Napier, Dan Wolf, Robert J. Paxton
A11: Team_Smith_OF_Group | B11: Official | C11: Public | D11: yes | E11: yes | F11: 8007 | G11: Rotary | H11: 12 | I11: 10 | J11: no | L11: yes | O11: Jeff_Stadler@glic.com,RCook@glic.com,shannon_bartlett@glic.com | P11: Pooja Konda, Anirban Chakravarty, Simonti Sen, Garrett Napier, Dan Wolf, Robert J. Paxton
A12: Broker_VM_Opt_Florida_DN_Group | B12: Official | C12: Public | D12: yes | E12: yes | F12: 8008 | G12: Rotary | H12: 12 | I12: 10 | J12: no | L12: yes | O12: Brittany_Collier@glic.com,Cynthia_Mateer@glic.com,Lisa_Manescu@glic.com,Wendy_Schoenberger@glic.com,megan_schalund@glic.com,brianna_crager@glic.com | P12: Pooja Konda, Anirban Chakravarty, Simonti Sen, Garrett Napier, Dan Wolf, Robert J. Paxton
A13: Team_Kober_OF_Group | B13: Official | C13: Public | D13: yes | E13: yes | F13: 8009 | G13: Rotary | H13: 12 | I13: 10 | J13: no | L13: yes | O13: amy_nyce@glic.com,angela_louros@glic.com,Beth_Ritchie@glic.com,bryan_mccray@glic.com,catherine_malitsis@glic.com,Charmaine_Espinoza@glic.com,Deb_Doyne@glic.com,Jennifer_VanHandel@glic.com,josey_wendler@glic.com,karen_hietpas@glic.com,Kayla_Murtaugh@glic.com,latoya_moore@glic.com,Lina_Alvarez@glic.com,Mandy_Otto@glic.com,michael_santos@glic.com,Michelle_Radtke@glic.com,natalie_indelicato@glic.com,ryan_p_thomas@glic.com,Sue_Reppert@glic.com | P13: Pooja Konda, Anirban Chakravarty, Simonti Sen, Garrett Napier, Dan Wolf, Robert J. Paxton
A14: Broker_VM_Opt_Greater_New_York_DN_Group | B14: Official | C14: Public | D14: yes | E14: yes | F14: 8010 | G14: Rotary | H14: 12 | I14: 10 | J14: no | L14: yes | O14: tammy_billheimer@glic.com,zach_kickbusch@glic.com,Ashlee_Mereness@glic.com,Cindy_Kriewaldt@glic.com,Michelle_Radtke@glic.com,Patricia_Young@glic.com,pamela_barrett@glic.com,Sandy_Vandermoss@glic.com,cindy_johnson@glic.com | P14: Pooja Konda, Anirban Chakravarty, Simonti Sen, Garrett Napier, Dan Wolf, Robert J. Paxton
A15: Broker_VM_Opt_Great_Lakes_DN_Group | B15: Official | C15: Public | D15: yes | E15: yes | F15: 8011 | G15: Rotary | H15: 12 | I15: 10 | J15: no | L15: yes | O15: Sara_Leitermann@glic.com,mitchell_roepcke@glic.com,Jessica_Knutson@glic.com,Barb_Hanson@glic.com,Natasha_Yancey@glic.com,sydney_hassler@glic.com,jennifer_lison@glic.com,laterrica_harris@glic.com | P15: Pooja Konda, Anirban Chakravarty, Simonti Sen, Garrett Napier, Dan Wolf, Robert J. Paxton
... A23: Broker_VM_Opt_Pacific_SW_DN_Group | B23: Official | C23: Public | D23: yes | E23: yes | F23: 8019 | G23: Rotary | H23: 12 | I23: 10 | J23: no | L23: yes | O23: Rebecca_Buchinger@glic.com,Vonnie_Riehle@glic.com,christa_powell@glic.com,katie_romo@glic.com,leigh_schneider@glic.com,hazel_delareto@glic.com,theresa_ludtke@glic.com | P23: Pooja Konda, Anirban Chakravarty, Simonti Sen, Garrett Napier, Dan Wolf, Robert J. Paxton
A24: Dental_Closed_Group | B24: Official | C24: Public | D24: yes | E24: yes | F24: 8020 | G24: Rotary | H24: 12 | I24: 10 | J24: no | L24: yes | P24: Pooja Konda, Anirban Chakravarty, Simonti Sen, Garrett Napier, Dan Wolf, Robert J. Paxton
A25: EDI_VM | B25: Official | C25: Public | D25: yes | E25: yes | F25: 8021 | G25: Rotary | H25: 12 | I25: 10 | J25: no | L25: yes | O25: AISVARIYA_R@glic.com,aman_hooda@glic.com,Ankit_Sher_Singh@glic.com,arjun_ekambaram@glic.com,bhuvaneswari_kaliyaperumal@glic.com,Cheshta_Singh@glic.com,christine_strickler@glic.com,david_r_kennedy@glic.com,deepak_pathak@glic.com,Gagan_Nawani@glic.com,Heather_Carpenter@glic.com,jamuna_x_kailasam@glic.com,jana_peterson@glic.com,Jeremy_Zeegers@glic.com,jonathan_gracer@glic.com,Kate_Hennessey@glic.com,kristen_aiello@glic.com,kristin_soldridge@glic.com,Kristine_Muench@glic.com,kumaresan_subramanian@glic.com,Lena_P_Xiong@glic.com,Lisa_A_Reier@glic.com,Mary_Zoromski@glic.com,matt_guidry@glic.com,maurice_tucker@glic.com,michael_ulmen@glic.com,mohit_dixit@glic.com,Nandakumar_Ganesan@glic.com,nicholas_kline@glic.com,nitesh_n@glic.com,noor-mohammed_methapillai-marasikayer@glic.com,pamela_stanek@glic.com,pratyush_jha@glic.com,Priya_Natarajan@glic.com,Rekha_Pandey@glic.com,senthamilmanimaran_karunanithi@glic.com,shafara_bridges@glic.com,shristi_singh@glic.com,simson_chellathurai@glic.com | P25: Pooja Konda, Anirban Chakravarty, Simonti Sen, Garrett Napier, Dan Wolf, Robert J. Paxton
A26: HW_Deduction_VM_Group | B26: Official | C26: Public | D26: yes | E26: yes | F26: 8022 | G26: Rotary | H26: 12 | I26: 10 | J26: no | L26: yes | P26: Pooja Konda, Anirban Chakravarty, Simonti Sen, Garrett Napier, Dan Wolf, Robert J. Paxton
A27: National_Conversion_Closed_Group | B27: Official | C27: Public | D27: yes | E27: yes | F27: 8023 | G27: Rotary | H27: 12 | I27: 10 | J27: no | L27: yes | O27: brandy_dunlow@glic.com,Cindy_Delfosse@glic.com,Denise_Eckert@glic.com,Leah_Williamson@glic.com,pamela_olson@glic.com,rebecca_jansen@glic.com,regina_nelson@glic.com,robin_dobberstein@glic.com | P27: Pooja Konda, Anirban Chakravarty, Simonti Sen, Garrett Napier, Dan Wolf, Robert J. Paxton
A28: National_Conversion_Exception_Group | B28: Official | C28: Public | D28: yes | E28: yes | F28: 8024 | G28: Rotary | H28: 12 | I28: 10 | J28: no | L28: yes | O28: brandy_dunlow@glic.com,Cindy_Delfosse@glic.com,Denise_Eckert@glic.com,Leah_Williamson@glic.com,pamela_olson@glic.com,rebecca_jansen@glic.com,regina_nelson@glic.com,robin_dobberstein@glic.com | P28: Pooja Konda, Anirban Chakravarty, Simonti Sen, Garrett Napier, Dan Wolf, Robert J. Paxton
A29: National_Conversion_Holiday_Group | B29: Official | C29: Public | D29: yes | E29: yes | F29: 8025 | G29: Rotary | H29: 12 | I29: 10 | J29: no | L29: yes | O29: brandy_dunlow@glic.com,Cindy_Delfosse@glic.com,Denise_Eckert@glic.com,Leah_Williamson@glic.com,pamela_olson@glic.com,rebecca_jansen@glic.com,regina_nelson@glic.com,robin_dobberstein@glic.com | P29: Pooja Konda, Anirban Chakravarty, Simonti Sen, Garrett Napier, Dan Wolf, Robert J. Paxton
A30: National_Conversion_Unstaffed_Group | B30: Official | C30: Public | D30: yes | E30: yes | F30: 8026 | G30: Rotary | H30: 12 | I30: 10 | J30: no | L30: yes | O30: brandy_dunlow@glic.com,Cindy_Delfosse@glic.com,Denise_Eckert@glic.com,Leah_Williamson@glic.com,pamela_olson@glic.com,rebecca_jansen@glic.com,regina_nelson@glic.com,robin_dobberstein@glic.com | P30: Pooja Konda, Anirban Chakravarty, Simonti Sen, Garrett Napier, Dan Wolf, Robert J. Paxton
A31: Premier_Planholder_Group | B31: Official | C31: Public | D31: yes | E31: yes | F31: 8027 | G31: Rotary | H31: 12 | I31: 10 | J31: no | L31: yes | O31: alicia_kettner@glic.com,amy_Erickson@glic.com,amy_vaupel@glic.com,Anna_Lee@glic.com,brandon_velez@glic.com,cynara_mayer@glic.com,Destiny_Harris@glic.com,Jennifer_Schoenick@glic.com,Karen_Miletto@glic.com,lindsay_shiner@glic.com,Mary_Krueger@glic.com,Melanie_Stellmach@glic.com,rachel_a_showman@glic.com,Randi_Trudeau@glic.com,selena_rippy@glic.com,Sue_Steffens@glic.com,trent_wright@glic.com | P31: Pooja Konda, Anirban Chakravarty, Simonti Sen, Garrett Napier, Dan Wolf, Robert J. Paxton
A32: IPSIEX_Closed_CA_Group | B32: Official | C32: Public | D32: yes | E32: yes | F32: 8028 | G32: Rotary | H32: 12 | I32: 10 | J32: no | L32: yes | P32: Pooja Konda, Anirban Chakravarty, Simonti Sen, Garrett Napier, Dan Wolf, Robert J. Paxton
A33: IL_LifeClaims_Unstaffed_Group | B33: Official | C33: Public | D33: yes | E33: yes | F33: 8029 | G33: Rotary | H33: 12 | I33: 10 | J33: no | L33: yes | P33: Pooja Konda, Anirban Chakravarty, Simonti Sen, Garrett Napier, Dan Wolf, Robert J. Paxton
A34: DI_DTC_Agency_Assist_Group | B34: Official | C34: Public | D34: yes | E34: yes | F34: 8030 | G34: Rotary | H34: 12 | I34: 10 | J34: no | L34: yes | P34: Pooja Konda, Anirban Chakravarty, Simonti Sen, Garrett Napier, Dan Wolf, Robert J. Paxton
A35: IM_Agent_Closed_Group | B35: Official | C35: Public | D35: yes | E35: yes | F35: 8031 | G35: Rotary | H35: 12 | I35: 10 | J35: no | L35: yes | P35: Pooja Konda, Anirban Chakravarty, Simonti Sen, Garrett Napier, Dan Wolf, Robert J. Paxton
A36: IM_Agent_Unstaffed_Group | B36: Official | C36: Public | D36: yes | E36: yes | F36: 8032 | G36: Rotary | H36: 12 | I36: 10 | J36: no | L36: yes | O36: luz_alvarado@glic.com | P36: Pooja Konda, Anirban Chakravarty, Simonti Sen, Garrett Napier, Dan Wolf, Robert J. Paxton
A37: CLM_Unstaffed_Group | B37: Official | C37: Public | D37: yes | E37: yes | F37: 8033 | G37: Rotary | H37: 12 | I37: 10 | J37: no | L37: yes | P37: Pooja Konda, Anirban Chakravarty, Simonti Sen, Garrett Napier, Dan Wolf, Robert J. Paxton
A38: IL_Elite_Group | B38: Official | C38: Public | D38: yes | E38: yes | F38: 8034 | G38: Rotary | H38: 12 | I38: 10 | J38: no | L38: yes | O38: Evangelista_Mora@glic.com,harrison_scheffler@glic.com,Krista_Demyan@glic.com,martin_goldstein@glic.com,samantha_kenyon@glic.com,warren_kwan@glic.com | P38: Pooja Konda, Anirban Chakravarty, Simonti Sen, Garrett Napier, Dan Wolf, Robert J. Paxton
A39: IL_LifeClaims_Closed_Group | B39: Official | C39: Public | D39: yes | E39: yes | F39: 8035 | G39: Rotary | H39: 12 | I39: 10 | J39: no | L39: yes | P39: Pooja Konda, Anirban Chakravarty, Simonti Sen, Garrett Napier, Dan Wolf, Robert J. Paxton
A40: IL_LifeClaims_Exception_Group | B40: Official | C40: Public | D40: yes | E40: yes | F40: 8036 | G40: Rotary | H40: 12 | I40: 10 | J40: no | L40: yes | P40: Pooja Konda, Anirban Chakravarty, Simonti Sen, Garrett Napier, Dan Wolf, Robert J. Paxton
A41: IL_LifeClaims_Holiday_Group | B41: Official | C41: Public | D41: yes | E41: yes | F41: 8037 | G41: Rotary | H41: 12 | I41: 10 | J41: no | L41: yes | P41: Pooja Konda, Anirban Chakravarty, Simonti Sen, Garrett Napier, Dan Wolf, Robert J. Paxton
A42: eApp_Unstaffed_Group | B42: Official | C42: Public | D42: yes | E42: yes | F42: 8038 | G42: Rotary | H42: 12 | I42: 10 | J42: no | L42: yes | P42: Pooja Konda, Anirban Chakravarty, Simonti Sen, Garrett Napier, Dan Wolf, Robert J. Paxton
A43: RSTPA_Closed_Group | B43: Official | C43: Public | D43: yes | E43: yes | F43: 8039 | G43: Rotary | H43: 12 | I43: 10 | J43: no | L43: yes | P43: Pooja Konda, Anirban Chakravarty, Simonti Sen, Garrett Napier, Dan Wolf, Robert J. Paxton
A44: GSA_Trading_Group | B44: Official | C44: Public | D44: yes | E44: yes | F44: 8040 | G44: Rotary | H44: 12 | I44: 10 | J44: no | L44: yes | P44: Pooja Konda, Anirban Chakravarty, Simonti Sen, Garrett Napier, Dan Wolf, Robert J. Paxton
A45: GSA_Client_Group | B45: Official | C45: Public | D45: yes | E45: yes | F45: 8041 | G45: Rotary | H45: 12 | I45: 10 | J45: no | L45: yes | P45: Pooja Konda, Anirban Chakravarty, Simonti Sen, Garrett Napier, Dan Wolf, Robert J. Paxton
A46: GSA_Advisor_Group | B46: Official | C46: Public | D46: yes | E46: yes | F46: 8042 | G46: Rotary | H46: 12 | I46: 10 | J46: no | L46: yes | P46: Pooja Konda, Anirban Chakravarty, Simonti Sen, Garrett Napier, Dan Wolf, Robert J. Paxton
A47: Tricia_VM_Group | B47: Official | C47: Public | D47: yes | E47: yes | F47: 8043 | G47: Rotary | H47: 12 | I47: 10 | J47: no | L47: yes | O47: brenna_kern@glic.com,Haripriya_Nagarajan@glic.com,karthikeyan_jaganathan@glic.com,Marlene_J_Dupuis@glic.com,Patrick_R_Harlan@glic.com,pavankumar_kothapalli@glic.com,simonti_test@glic.com | P47: Pooja Konda, Anirban Chakravarty, Simonti Sen, Garrett Napier, Dan Wolf, Robert J. Paxton
A48: Suzanne_VM_Group | B48: Official | C48: Public | D48: yes | E48: yes | F48: 8044 | G48: Rotary | H48: 12 | I48: 10 | J48: no | L48: yes | O48: brenna_kern@glic.com,Haripriya_Nagarajan@glic.com,karthikeyan_jaganathan@glic.com,Marlene_J_Dupuis@glic.com,Patrick_R_Harlan@glic.com,pavankumar_kothapalli@glic.com,simonti_test@glic.com | P48: Pooja Konda, Anirban Chakravarty, Simonti Sen, Garrett Napier, Dan Wolf, Robert J. Paxton
A49: Salt_Lake_City_QX_Unstaffed_Group | B49: Official | C49: Public | D49: yes | E49: yes | F49: 8045 | G49: Rotary | H49: 12 | I49: 10 | J49: no | L49: yes | P49: Pooja Konda, Anirban Chakravarty, Simonti Sen, Garrett Napier, Dan Wolf, Robert J. Paxton
A50: Salt_Lake_City_QX_Holiday_Group | B50: Official | C50: Public | D50: yes | E50: yes | F50: 8046 | G50: Rotary | H50: 12 | I50: 10 | J50: no | L50: yes | P50: Pooja Konda, Anirban Chakravarty, Simonti Sen, Garrett Napier, Dan Wolf, Robert J. Paxton
A51: Salt_Lake_City_QX_Closed_Group | B51: Official | C51: Public | D51: yes | E51: yes | F51: 8047 | G51: Rotary | H51: 12 | I51: 10 | J51: no | L51: yes | P51: Pooja Konda, Anirban Chakravarty, Simonti Sen, Garrett Napier, Dan Wolf, Robert J. Paxton
A52: OPC_Unstaffed_Group | B52: Official | C52: Public | D52: yes | E52: yes | F52: 8048 | G52: Rotary | H52: 12 | I52: 10 | J52: no | L52: yes | P52: Pooja Konda, Anirban Chakravarty, Simonti Sen, Garrett Napier, Dan Wolf, Robert J. Paxton
A53: OPC_Holiday_Group | B53: Official | C53: Public | D53: yes | E53: yes | F53: 8049 | G53: Rotary | H53: 12 | I53: 10 | J53: no | L53: yes | P53: Pooja Konda, Anirban Chakravarty, Simonti Sen, Garrett Napier, Dan Wolf, Robert J. Paxton
A54: OPC_Closed_Group | B54: Official | C54: Public | D54: yes | E54: yes | F54: 8050 | G54: Rotary | H54: 12 | I54: 10 | J54: no | L54: yes | P54: Pooja Konda, Anirban Chakravarty, Simonti Sen, Garrett Napier, Dan Wolf, Robert J. Paxton
A55: Megan_VM_Group | B55: Official | C55: Public | D55: yes | E55: yes | F55: 8051 | G55: Rotary | H55: 12 | I55: 10 | J55: no | L55: yes | O55: brenna_kern@glic.com,Haripriya_Nagarajan@glic.com,karthikeyan_jaganathan@glic.com,Marlene_J_Dupuis@glic.com,Patrick_R_Harlan@glic.com,pavankumar_kothapalli@glic.com,simonti_test@glic.com | P55: Pooja Konda, Anirban Chakravarty, Simonti Sen, Garrett Napier, Dan Wolf, Robert J. Paxton
A56: MCM_Unstaffed_Group | B56: Official | C56: Public | D56: yes | E56: yes | F56: 8052 | G56: Rotary | H56: 12 | I56: 10 | J56: no | L56: yes | P56: Pooja Konda, Anirban Chakravarty, Simonti Sen, Garrett Napier, Dan Wolf, Robert J. Paxton
A57: MCM_Holiday_Group | B57: Official | C57: Public | D57: yes | E57: yes | F57: 8053 | G57: Rotary | H57: 12 | I57: 10 | J57: no | L57: yes | P57: Pooja Konda, Anirban Chakravarty, Simonti Sen, Garrett Napier, Dan Wolf, Robert J. Paxton
A58: MCM_Exception_Group | B58: Official | C58: Public | D58: yes | E58: yes | F58: 8054 | G58: Rotary | H58: 12 | I58: 10 | J58: no | L58: yes | P58: Pooja Konda, Anirban Chakravarty, Simonti Sen, Garrett Napier, Dan Wolf, Robert J. Paxton
A59: MCM_Closed_Group | B59: Official | C59: Public | D59: yes | E59: yes | F59: 8055 | G59: Rotary | H59: 12 | I59: 10 | J59: no | L59: yes | P59: Pooja Konda, Anirban Chakravarty, Simonti Sen, Garrett Napier, Dan Wolf, Robert J. Paxton
A60: Mary_VM_Group | B60: Official | C60: Public | D60: yes | E60: yes | F60: 8056 | G60: Rotary | H60: 12 | I60: 10 | J60: no | L60: yes | O60: brenna_kern@glic.com,Haripriya_Nagarajan@glic.com,karthikeyan_jaganathan@glic.com,Marlene_J_Dupuis@glic.com,Patrick_R_Harlan@glic.com,pavankumar_kothapalli@glic.com,simonti_test@glic.com | P60: Pooja Konda, Anirban Chakravarty, Simonti Sen, Garrett Napier, Dan Wolf, Robert J. Paxton
A61: Marlene_VM_Group | B61: Official | C61: Public | D61: yes | E61: yes | F61: 8057 | G61: Rotary | H61: 12 | I61: 10 | J61: no | L61: yes | O61: brenna_kern@glic.com,Haripriya_Nagarajan@glic.com,karthikeyan_jaganathan@glic.com,Marlene_J_Dupuis@glic.com,Patrick_R_Harlan@glic.com,pavankumar_kothapalli@glic.com,simonti_test@glic.com | P61: Pooja Konda, Anirban Chakravarty, Simonti Sen, Garrett Napier, Dan Wolf, Robert J. Paxton
A62: Lisa_VM_Group | B62: Official | C62: Public | D62: yes | E62: yes | F62: 8058 | G62: Rotary | H62: 12 | I62: 10 | J62: no | L62: yes | O62: brenna_kern@glic.com,Haripriya_Nagarajan@glic.com,karthikeyan_jaganathan@glic.com,Marlene_J_Dupuis@glic.com,Patrick_R_Harlan@glic.com,pavankumar_kothapalli@glic.com,simonti_test@glic.com | P62: Pooja Konda, Anirban Chakravarty, Simonti Sen, Garrett Napier, Dan Wolf, Robert J. Paxton
A63: Judy_VM_Group | B63: Official | C63: Public | D63: yes | E63: yes | F63: 8059 | G63: Rotary | H63: 12 | I63: 10 | J63: no | L63: yes | O63: brenna_kern@glic.com,Haripriya_Nagarajan@glic.com,karthikeyan_jaganathan@glic.com,Marlene_J_Dupuis@glic.com,Patrick_R_Harlan@glic.com,pavankumar_kothapalli@glic.com,simonti_test@glic.com | P63: Pooja Konda, Anirban Chakravarty, Simonti Sen, Garrett Napier, Dan Wolf, Robert J. Paxton
A64: EDI_VM_Group | B64: Official | C64: Public | D64: yes | E64: yes | F64: 8060 | G64: Rotary | H64: 12 | I64: 10 | J64: no | L64: yes | O64: AISVARIYA_R@glic.com,aman_hooda@glic.com,Ankit_Sher_Singh@glic.com,arjun_ekambaram@glic.com,bhuvaneswari_kaliyaperumal@glic.com,Cheshta_Singh@glic.com,christine_strickler@glic.com,david_r_kennedy@glic.com,deepak_pathak@glic.com,Gagan_Nawani@glic.com,Heather_Carpenter@glic.com,jamuna_x_kailasam@glic.com,jana_peterson@glic.com,Jeremy_Zeegers@glic.com,jonathan_gracer@glic.com,Kate_Hennessey@glic.com,kristen_aiello@glic.com,kristin_soldridge@glic.com,Kristine_Muench@glic.com,kumaresan_subramanian@glic.com,Lena_P_Xiong@glic.com,Lisa_A_Reier@glic.com,Mary_Zoromski@glic.com,matt_guidry@glic.com,maurice_tucker@glic.com,michael_ulmen@glic.com,mohit_dixit@glic.com,Nandakumar_Ganesan@glic.com,nicholas_kline@glic.com,nitesh_n@glic.com,noor-mohammed_methapillai-marasikayer@glic.com,pamela_stanek@glic.com,pratyush_jha@glic.com,Priya_Natarajan@glic.com,Rekha_Pandey@glic.com,senthamilmanimaran_karunanithi@glic.com,shafara_bridges@glic.com,shristi_singh@glic.com,simson_chellathurai@glic.com | P64: Pooja Konda, Anirban Chakravarty, Simonti Sen, Garrett Napier, Dan Wolf, Robert J. Paxton
A65: CDC_Closed_Group | B65: Official | C65: Public | D65: yes | E65: yes | F65: 8061 | G65: Rotary | H65: 12 | I65: 10 | J65: no | L65: yes | P65: Pooja Konda, Anirban Chakravarty, Simonti Sen, Garrett Napier, Dan Wolf, Robert J. Paxton
A66: Brianna_VM_Group | B66: Official | C66: Public | D66: yes | E66: yes | F66: 8062 | G66: Rotary | H66: 12 | I66: 10 | J66: no | L66: yes | O66: Suzanne_Seguin@glic.com,Lisa_M_Nagy@glic.com,Judy_Adler@glic.com,brenna_kern@glic.com,pavankumar_kothapalli@glic.com,karthikeyan_jaganathan@glic.com,Brianna_Zischang@glic.com | P66: Pooja Konda, Anirban Chakravarty, Simonti Sen, Garrett Napier, Dan Wolf, Robert J. Paxton
A67: BRC_VM_Group | B67: Official | C67: Public | D67: yes | E67: yes | F67: 8063 | G67: Rotary | H67: 12 | I67: 10 | J67: no | L67: yes | P67: Pooja Konda, Anirban Chakravarty, Simonti Sen, Garrett Napier, Dan Wolf, Robert J. Paxton
A68: BRC_Unstaffed_Group | B68: Official | C68: Public | D68: yes | E68: yes | F68: 8064 | G68: Rotary | H68: 12 | I68: 10 | J68: no | L68: yes | P68: Pooja Konda, Anirban Chakravarty, Simonti Sen, Garrett Napier, Dan Wolf, Robert J. Paxton
A69: BRC_Holiday_Group | B69: Official | C69: Public | D69: yes | E69: yes | F69: 8065 | G69: Rotary | H69: 12 | I69: 10 | J69: no | L69: yes | P69: Pooja Konda, Anirban Chakravarty, Simonti Sen, Garrett Napier, Dan Wolf, Robert J. Paxton
A70: BRC_Exception_Group | B70: Official | C70: Public | D70: yes | E70: yes | F70: 8066 | G70: Rotary | H70: 12 | I70: 10 | J70: no | L70: yes | P70: Pooja Konda, Anirban Chakravarty, Simonti Sen, Garrett Napier, Dan Wolf, Robert J. Paxton
A71: BRC_Closed_Group | B71: Official | C71: Public | D71: yes | E71: yes | F71: 8067 | G71: Rotary | H71: 12 | I71: 10 | J71: no | L71: yes | P71: Pooja Konda, Anirban Chakravarty, Simonti Sen, Garrett Napier, Dan Wolf, Robert J. Paxton
A72: ASL_Unstaffed_Group | B72: Official | C72: Public | D72: yes | E72: yes | F72: 8068 | G72: Rotary | H72: 12 | I72: 10 | J72: no | L72: yes | O72: Suzanne_Seguin@glic.com,Lisa_M_Nagy@glic.com,Judy_Adler@glic.com,brenna_kern@glic.com,margaux_c_rigoland@glic.com,Eric_Littman@glic.com,anthony_letizia@glic.com,kristopher_ireland@glic.com,Kristina_Nash@glic.com,michelle_turpin@glic.com,pavankumar_kothapalli@glic.com,karthikeyan_jaganathan@glic.com,Brianna_Zischang@glic.com,lauren_fetherman@glic.com,madalene_harden@glic.com | P72: Pooja Konda, Anirban Chakravarty, Simonti Sen, Garrett Napier, Dan Wolf, Robert J. Paxton
A73: ASL_Closed_Group | B73: Official | C73: Public | D73: yes | E73: yes | F73: 8069 | G73: Rotary | H73: 12 | I73: 10 | J73: no | L73: yes | O73: Suzanne_Seguin@glic.com,Lisa_M_Nagy@glic.com,Judy_Adler@glic.com,brenna_kern@glic.com,margaux_c_rigoland@glic.com,Eric_Littman@glic.com,anthony_letizia@glic.com,kristopher_ireland@glic.com,Kristina_Nash@glic.com,michelle_turpin@glic.com,pavankumar_kothapalli@glic.com,karthikeyan_jaganathan@glic.com,Brianna_Zischang@glic.com,lauren_fetherman@glic.com,madalene_harden@glic.com | P73: Pooja Konda, Anirban Chakravarty, Simonti Sen, Garrett Napier, Dan Wolf, Robert J. Paxton
A74: ASL_ClientID_VM_Group | B74: Official | C74: Public | D74: yes | E74: yes | F74: 8070 | G74: Rotary | H74: 12 | I74: 10 | J74: no | L74: yes | O74: Suzanne_Seguin@glic.com,Lisa_M_Nagy@glic.com,Judy_Adler@glic.com,brenna_kern@glic.com,margaux_c_rigoland@glic.com,Eric_Littman@glic.com,anthony_letizia@glic.com,kristopher_ireland@glic.com,Kristina_Nash@glic.com,michelle_turpin@glic.com,pavankumar_kothapalli@glic.com,karthikeyan_jaganathan@glic.com,Brianna_Zischang@glic.com,lauren_fetherman@glic.com,madalene_harden@glic.com | P74: Pooja Konda, Anirban Chakravarty, Simonti Sen, Garrett Napier, Dan Wolf, Robert J. Paxton
A75: ASL_ClientID_1111_VM_Group | B75: Official | C75: Public | D75: yes | E75: yes | F75: 8071 | G75: Rotary | H75: 12 | I75: 10 | J75: no | L75: yes | O75: Suzanne_Seguin@glic.com,Lisa_M_Nagy@glic.com,Judy_Adler@glic.com,brenna_kern@glic.com,margaux_c_rigoland@glic.com,Eric_Littman@glic.com,anthony_letizia@glic.com,kristopher_ireland@glic.com,Kristina_Nash@glic.com,michelle_turpin@glic.com,pavankumar_kothapalli@glic.com,karthikeyan_jaganathan@glic.com,Brianna_Zischang@glic.com,lauren_fetherman@glic.com,madalene_harden@glic.com | P75: Pooja Konda, Anirban Chakravarty, Simonti Sen, Garrett Napier, Dan Wolf, Robert J. Paxton
A76: Altfunded_Unstaffed_Group | B76: Official | C76: Public | D76: yes | E76: yes | F76: 8072 | G76: Rotary | H76: 12 | I76: 10 | J76: no | L76: yes | P76: Pooja Konda, Anirban Chakravarty, Simonti Sen, Garrett Napier, Dan Wolf, Robert J. Paxton
A77: Altfunded_Closed_Group | B77: Official | C77: Public | D77: yes | E77: yes | F77: 8073 | G77: Rotary | H77: 12 | I77: 10 | J77: no | L77: yes | P77: Pooja Konda, Anirban Chakravarty, Simonti Sen, Garrett Napier, Dan Wolf, Robert J. Paxton
A78: ACL_Closed_Group | B78: Official | C78: Public | D78: yes | E78: yes | F78: 8074 | G78: Rotary | H78: 12 | I78: 10 | J78: no | L78: yes | O78: ashley_sosa@glic.com,breanna_bradley@glic.com,Courtney_Ross@glic.com,Jacquelyn_Perez@glic.com,jamie_x_strohecker1@glic.com,kim_a_markline@glic.com,laura_maria_cachinero@glic.com,lavern_mcqueen@glic.com,lori_x_averna@glic.com,natasha_bonyun@glic.com,priscila_barbavital@glic.com,tarek_diab@glic.com,Cheri_Semmel@glic.com,francescoa_alatrista-lerzundi@glic.com,kathleen_dejulio@glic.com,Suzanne_Seguin@glic.com,Lisa_M_Nagy@glic.com,Judy_Adler@glic.com,brenna_kern@glic.com,margaux_c_rigoland@glic.com,Eric_Littman@glic.com,anthony_letizia@glic.com,kristopher_ireland@glic.com,Kristina_Nash@glic.com,michelle_turpin@glic.com,pavankumar_kothapalli@glic.com,karthikeyan_jaganathan@glic.com,Brianna_Zischang@glic.com,tara_gubitosi@glic.com,sara_desjadon@glic.com,jayne_x_civitella@glic.com,bruce_delong@glic.com,amanda_schneck@glic.com,lauren_fetherman@glic.com,madalene_harden@glic.com | P78: Pooja Konda, Anirban Chakravarty, Simonti Sen, Garrett Napier, Dan Wolf, Robert J. Paxton
A79: Finance_Assist_Group | B79: Official | C79: Public | D79: yes | E79: yes | F79: 8075 | G79: Rotary | H79: 12 | I79: 10 | J79: no | L79: yes | P79: Pooja Konda, Anirban Chakravarty, Simonti Sen, Garrett Napier, Dan Wolf, Robert J. Paxton
A80: G888_UP_Group | B80: Official | C80: Public | D80: yes | E80: yes | F80: 8076 | G80: Rotary | H80: 12 | I80: 10 | J80: no | L80: yes | P80: Pooja Konda, Anirban Chakravarty, Simonti Sen, Garrett Napier, Dan Wolf, Robert J. Paxton
A81: ACL_VM_Group | B81: Official | C81: Public | D81: yes | E81: yes | F81: 8077 | G81: Rotary | H81: 12 | I81: 10 | J81: no | L81: yes | O81: ashley_sosa@glic.com,breanna_bradley@glic.com,Courtney_Ross@glic.com,Jacquelyn_Perez@glic.com,jamie_x_strohecker1@glic.com,kim_a_markline@glic.com,laura_maria_cachinero@glic.com,lavern_mcqueen@glic.com,lori_x_averna@glic.com,natasha_bonyun@glic.com,priscila_barbavital@glic.com,tarek_diab@glic.com,Cheri_Semmel@glic.com,francescoa_alatrista-lerzundi@glic.com,kathleen_dejulio@glic.com,Suzanne_Seguin@glic.com,Lisa_M_Nagy@glic.com,Judy_Adler@glic.com,brenna_kern@glic.com,margaux_c_rigoland@glic.com,Eric_Littman@glic.com,anthony_letizia@glic.com,kristopher_ireland@glic.com,Kristina_Nash@glic.com,michelle_turpin@glic.com,pavankumar_kothapalli@glic.com,karthikeyan_jaganathan@glic.com,Brianna_Zischang@glic.com,tara_gubitosi@glic.com,sara_desjadon@glic.com,jayne_x_civitella@glic.com,bruce_delong@glic.com,amanda_schneck@glic.com,lauren_fetherman@glic.com,madalene_harden@glic.com | P81: Pooja Konda, Anirban Chakravarty, Simonti Sen, Garrett Napier, Dan Wolf, Robert J. Paxton
A82: AASM_agallio_Group | B82: Official | C82: Public | D82: yes | E82: yes | F82: 8078 | G82: Rotary | H82: 12 | I82: 10 | J82: no | L82: yes | O82: agatha_gallion@glic.com | P82: Pooja Konda, Anirban Chakravarty, Simonti Sen, Garrett Napier, Dan Wolf, Robert J. Paxton
A83: AASM_areed02_Group | B83: Official | C83: Public | D83: yes | E83: yes | F83: 8079 | G83: Rotary | H83: 12 | I83: 10 | J83: no | L83: yes | O83: Alyssa_Reed@glic.com | P83: Pooja Konda, Anirban Chakravarty, Simonti Sen, Garrett Napier, Dan Wolf, Robert J. Paxton
A84: AASM_amatcza_Group | B84: Official | C84: Public | D84: yes | E84: yes | F84: 8080 | G84: Rotary | H84: 12 | I84: 10 | J84: no | L84: yes | O84: Amanda_Matczak@glic.com | P84: Pooja Konda, Anirban Chakravarty, Simonti Sen, Garrett Napier, Dan Wolf, Robert J. Paxton
A85: AASM_abritti_Group | B85: Official | C85: Public | D85: yes | E85: yes | F85: 8081 | G85: Rotary | H85: 12 | I85: 10 | J85: no | L85: yes | O85: amber_brittian@glic.com | P85: Pooja Konda, Anirban Chakravarty, Simonti Sen, Garrett Napier, Dan Wolf, Robert J. Paxton
A86: AASM_arice01_Group | B86: Official | C86: Public | D86: yes | E86: yes | F86: 8082 | G86: Rotary | H86: 12 | I86: 10 | J86: no | L86: yes | O86: amber_rice@glic.com | P86: Pooja Konda, Anirban Chakravarty, Simonti Sen, Garrett Napier, Dan Wolf, Robert J. Paxton
A87: AASM_nelgaxn_Group | B87: Official | C87: Public | D87: yes | E87: yes | F87: 8083 | G87: Rotary | H87: 12 | I87: 10 | J87: no | L87: yes | O87: amy_nyce@glic.com | P87: Pooja Konda, Anirban Chakravarty, Simonti Sen, Garrett Napier, Dan Wolf, Robert J. Paxton
A88: AASM_alouros_Group | B88: Official | C88: Public | D88: yes | E88: yes | F88: 8084 | G88: Rotary | H88: 12 | I88: 10 | J88: no | L88: yes | O88: angela_louros@glic.com | P88: Pooja Konda, Anirban Chakravarty, Simonti Sen, Garrett Napier, Dan Wolf, Robert J. Paxton
A89: AASM_chslaxc_Group | B89: Official | C89: Public | D89: yes | E89: yes | F89: 8085 | G89: Rotary | H89: 12 | I89: 10 | J89: no | L89: yes | O89: asha_cull@glic.com | P89: Pooja Konda, Anirban Chakravarty, Simonti Sen, Garrett Napier, Dan Wolf, Robert J. Paxton
A90: AASM_mgccalm_Group | B90: Official | C90: Public | D90: yes | E90: yes | F90: 8086 | G90: Rotary | H90: 12 | I90: 10 | J90: no | L90: yes | O90: Ashlee_Mereness@glic.com | P90: Pooja Konda, Anirban Chakravarty, Simonti Sen, Garrett Napier, Dan Wolf, Robert J. Paxton
A91: AASM_w848_Group | B91: Official | C91: Public | D91: yes | E91: yes | F91: 8087 | G91: Rotary | H91: 12 | I91: 10 | J91: no | L91: yes | O91: Barb_Hanson@glic.com | P91: Pooja Konda, Anirban Chakravarty, Simonti Sen, Garrett Napier, Dan Wolf, Robert J. Paxton
A92: AASM_mcrubxl_Group | B92: Official | C92: Public | D92: yes | E92: yes | F92: 8088 | G92: Rotary | H92: 12 | I92: 10 | J92: no | L92: yes | O92: barbara_leach@glic.com | P92: Pooja Konda, Anirban Chakravarty, Simonti Sen, Garrett Napier, Dan Wolf, Robert J. Paxton
... A201: AASM_crbszxk_Group | B201: Official | C201: Public | D201: yes | E201: yes | F201: 8197 | G201: Rotary | H201: 12 | I201: 10 | J201: no | L201: yes | O201: zach_kickbusch@glic.com | P201: Pooja Konda, Anirban Chakravarty, Simonti Sen, Garrett Napier, Dan Wolf, Robert J. Paxton
A202: Broker_VM_Opt_Broker_Sequoia_OF_Group | B202: Official | C202: Public | D202: yes | E202: yes | F202: 8198 | G202: Rotary | H202: 12 | I202: 10 | J202: no | L202: yes | P202: Pooja Konda, Anirban Chakravarty, Simonti Sen,QA users

Sheet Groups - Skill Expressions
A1: Skill Expression | Q1: About groups - Genesys Cloud Resource Center (mypurecloud.com)
A2: Skills Expression Groups_values only.xlsx | B2: see spreadsheet for details

Sheet External Contacts
A1: External Contacts | D1: About External Contacts - Genesys Cloud Resource Center (mypurecloud.com)
A2: Contact ID | B2: Contact First Name | C2: Contact Last Name | D2: Phone Number | E2: Built Prod | F2: Built Dev
A3: 12125988000 | B3: CRP_Operators | C3: IVR | D3: +12125988000 | E3: Yes | F3: Yes
A4: 12125988016 | B4: MDRT / Joe Cox | C4: External | D4: +12125988016 | E4: Yes | F4: Yes
A5: 12125988327 | B5: S2P Help Desk | C5: External | D5: +12125988327 | E5: Yes | F5: Yes
A6: 12125988386 | B6: Proxy Voting - Rose Romano | C6: External | D6: +12125988386 | E6: Yes | F6: Yes
A7: 12129192148 | B7: Mail Room - Hudson Yards | C7: External | D7: +12129192148 | E7: Yes | F7: Yes
A8: 12129192150 | B8: Reg. 60 / Jevon Aarons - Fax 212-919-4016 | C8: External | D8: +12129192150 | E8: Yes | F8: Yes
A9: 12129192386 | B9: Annuity Sales Desk / Business Development | C9: External | D9: +12129192386 | E9: Yes | F9: Yes
A10: 12129192699 | B10: Cafe - Hudson Yards | C10: External | D10: +12129192699 | E10: Yes | F10: Yes
A11: 12129192986 | B11: Security - Hudson Yards | C11: External | D11: +12129192986 | E11: Yes | F11: Yes
A12: 12129193036 | B12: Subrogation & Bankruptcy / Arleta Strus | C12: External | D12: +12129193036 | E12: Yes | F12: Yes
A13: 12129194558 | B13: Lost and Found - Hudson Yards | C13: External | D13: +12129194558 | E13: Yes | F13: Yes
A14: 12129195021 | B14: Security - Holmdel | C14: External | D14: +12129195021 | E14: Yes | F14: Yes
... A25: 14133954100 | B25: Berkshire Office | C25: External | D25: +14133954100 | E25: Yes | F25: Yes
A26: 14133954100B | B26: Security - Pittsfield / Berkshire | C26: External | D26: +14133954100 | E26: Yes | F26: Yes
A27: 14133954305 | B27: Cafe - Pittsfield | C27: External | D27: +14133954305 | E27: Yes | F27: Yes
A28: 14133954644 | B28: Mail Room - Berkshire/ Pittsfield - Kathleen Loria | C28: External | D28: +14133954644 | E28: Yes | F28: Yes
A29: 14133954791 | B29: Subpoenas / Subrogation - Amanda Carpenter - send subpoenas Certified to HO Attn Law Dept | C29: External | D29: +14133954791 | E29: Yes | F29: Yes
A30: 15083088396 | B30: Jim Magner / BRC | C30: External | D30: +15083088396 | E30: Yes | F30: Yes
A31: 15094686000 | B31: CRP_WROMainMenu | C31: IVR | D31: +15094686000 | E31: Yes | F31: Yes
A32: 15094686724 | B32: Cafe - Spokane | C32: External | D32: +15094686724 | E32: Yes | F32: Yes
A33: 15551001524 | B33: IPS_DTC | C33: IVR | D33: +15551001524 | E33: Yes | F33: Yes
A34: 15552220094 | B34: IM_PDA | C34: IVR | D34: +15552220094 | E34: Yes | F34: Yes
A35: 15555554008 | B35: GRP_STD | C35: IVR | D35: +15555554008 | E35: Yes | F35: Yes
A36: 15555554096 | B36: IPS_IEX | C36: IVR | D36: +15555554096 | E36: Yes | F36: Yes
A37: 15555559005 | B37: CRP_HR | C37: IVR | D37: +15555559005 | E37: Yes | F37: Yes
A38: 15555559033 | B38: GRP_TPAMenu | C38: IVR | D38: +15555559033 | E38: Yes | F38: Yes
... A326: 18002682525 | B326: State Disability / Paid Family Leave / STD | C326: External | D326: +18002682525 | E326: Yes | F326: Yes
A327: 18002682525B | B327: Group - STD Claims | C327: External | D327: +18002682525 | E327: Yes | F327: Yes
A328: 18002733330 | B328: GRP_MDC | C328: IVR | D328: +18002733330 | E328: Yes | F328: Yes
A329: 18002891337 | B329: Sykes Payment | C329: External | D329: +18002891337 | E329: Yes | F329: Yes
A330: 18002998654 | B330: Guardian Corporate Help Desk | C330: IVR | D330: +18002998654 | E330: Yes | F330: Yes
A331: 18003164015 | B331: ASL | C331: IVR | D331: +18003164015 | E331: Yes | F331: Yes
A332: 18003477443 | B332: Reed Group | C332: External | D332: +18003477443 | E332: Yes | F332: Yes
A333: 18003507314 | B333: IM_ICD | C333: IVR | D333: +18003507314 | E333: Yes | F333: Yes
A334: 18003565808 | B334: SGS / Small Group Sales Bethlehem | C334: External | D334: +18003565808 | E334: Yes | F334: Yes
A335: 18003867055 | B335: EAP - Member - Employee Assistance Program - M-F 9 to 8 Eastern | C335: External | D335: +18003867055 | E335: Yes | F335: Yes
A336: 18004335982 | B336: Group National Conversion Toll Free - Opt. 1 ext. 5696 - for Group policies that have been converted. | C336: External | D336: +18004335982 | E336: Yes | F336: Yes
A337: 18004335982B | B337: GRP_MRO_GCA | C337: IVR | D337: +18004335982 | E337: Yes | F337: Yes
A338: 18004416455 | B338: IMCC General IVR | C338: External | D338: +18004416455 | E338: Yes | F338: Yes
A339: 18004467872 | B339: Innovative Underwriters | C339: External | D339: +18004467872 | E339: Yes | F339: Yes
A340: 18004599401 | B340: GRP_Admin | C340: IVR | D340: +18004599401 | E340: Yes | F340: Yes
A341: 18004684015 | B341: GPT | C341: IVR | D341: +18004684015 | E341: Yes | F341: Yes
A342: 18004775908 | B342: Fraud Toll Free - if bank thinks they have a fraudulent check-transfer to Edmond Supple | C342: External | D342: +18004775908 | E342: Yes | F342: Yes
A343: 18004998820 | B343: Guardian Agency Help Desk | C343: External | D343: +18004998820 | E343: Yes | F343: Yes
A344: 18005115801 | B344: IM_Agent_Assist_New | C344: IVR | D344: +18005115801 | E344: Yes | F344: Yes
A345: 18005244542 | B345: Medical Coverage before 11-15-2012 - Must leave VM w/Name & Phone Number. Will receive call back within 24 hrs. | C345: External | D345: +18005244542 | E345: Yes | F345: Yes
A346: 18005254542 | B346: GRP_LifeClaims | C346: IVR | D346: +18005254542 | E346: Yes | F346: Yes
A347: 18005384583 | B347: Group - LTD Claims | C347: External | D347: +18005384583 | E347: Yes | F347: Yes
A348: 18005393863 | B348: Victory/RS Funds Client | C348: External | D348: +18005393863 | E348: Yes | F348: Yes
A349: 18005417846 | B349: Dental IVR - Accident / Cancer / Wellness Check | C349: IVR | D349: +18005417846 | E349: Yes | F349: Yes
A350: 18005417846B | B350: Dental Member Services | C350: IVR | D350: +18005417846 | E350: Yes | F350: Yes
A351: 18005417846C | B351: GRP_Dental | C351: IVR | D351: +18005417846 | E351: Yes | F351: Yes
A352: 18006244050 | B352: IPS_HealthStatement | C352: IVR | D352: +18006244050 | E352: Yes | F352: Yes
A353: 18006274200 | B353: Guardian Anytime | C353: IVR | D353: +18006274200 | E353: Yes | F353: Yes
A354: 18006274200B | B354: Group IVR | C354: IVR | D354: +18006274200 | E354: Yes | F354: Yes
A355: 18006303609 | B355: Talcott Agent | C355: External | D355: +18006303609 | E355: Yes | F355: Yes
A356: 18006490482 | B356: EFT - Dental Providers - option 4 (Change Health Care) | C356: External | D356: +18006490482 | E356: Yes | F356: Yes
A357: 18006506505 | B357: Annuity Sales | C357: IVR | D357: +18006506505 | E357: Yes | F357: Yes
A358: 18006506505B | B358: GIAC Annuity Sales Desk IVR | C358: IVR | D358: +18006506505 | E358: Yes | F358: Yes
A359: 18006506505C | B359: IM_QSDAnnuity | C359: IVR | D359: +18006506505 | E359: Yes | F359: Yes
A360: 18006854542 | B360: GRP_Onboarding | C360: IVR | D360: +18006854542 | E360: Yes | F360: Yes
A361: 18007328242 | B361: Altfunded_SelfInsured | C361: IVR | D361: +18007328242 | E361: Yes | F361: Yes
A362: 18007656405 | B362: GRP_AFTRA | C362: IVR | D362: +18007656405 | E362: Yes | F362: Yes
A363: 18007663863 | B363: RS Investments / 401k Sales | C363: External | D363: +18007663863 | E363: Yes | F363: Yes
A364: 18007752246 | B364: GRP_Advocate | C364: IVR | D364: +18007752246 | E364: Yes | F364: Yes
A365: 18007763925 | B365: CDC | C365: IVR | D365: +18007763925 | E365: Yes | F365: Yes
A366: 18008017649 | B366: IM_DTC | C366: IVR | D366: +18008017649 | E366: Yes | F366: Yes
A367: 18008192468 | B367: IM_CSC | C367: IVR | D367: +18008192468 | E367: Yes | F367: Yes
A368: 18008304147 | B368: Talcott Client | C368: External | D368: +18008304147 | E368: Yes | F368: Yes
A369: 18008484567 | B369: GRP_LargeCase | C369: IVR | D369: +18008484567 | E369: Yes | F369: Yes
A370: 18008658731 | B370: IM_ILCC | C370: IVR | D370: +18008658731 | E370: Yes | F370: Yes
A371: 18008717780 | B371: BRC / Product Support / APEX Group | C371: IVR | D371: +18008717780 | E371: Yes | F371: Yes
A372: 18008717780B | B372: Individual Life Conservation / Product Support | C372: IVR | D372: +18008717780 | E372: Yes | F372: Yes
A373: 18008717780C | B373: APEX Group / BRC / Life Product Support / Conservation / Shadow Advisors | C373: IVR | D373: +18008717780 | E373: Yes | F373: Yes
A374: 18008717780D | B374: Life Product Support | C374: IVR | D374: +18008717780 | E374: Yes | F374: Yes
A375: 18008717780E | B375: Broker Quote Req - Life | C375: IVR | D375: +18008717780 | E375: Yes | F375: Yes
A376: 18008717780F | B376: IM | C376: IVR | D376: +18008717780 | E376: Yes | F376: Yes
A377: 18008777195 | B377: VSP | C377: External | D377: +18008777195 | E377: Yes | F377: Yes
A378: 18008796934 | B378: IM_PASAdvisory | C378: IVR | D378: +18008796934 | E378: Yes | F378: Yes
A379: 18008902475 | B379: Dental for Guardian Employees | C379: IVR | D379: +18008902475 | E379: Yes | F379: Yes
A380: 18008902475B | B380: EB Dental IVR | C380: IVR | D380: +18008902475 | E380: Yes | F380: Yes
A381: 18008902475C | B381: GRP_EB | C381: IVR | D381: +18008902475 | E381: Yes | F381: Yes
A382: 18008904774 | B382: Dental Provider - Toll Free | C382: External | D382: +18008904774 | E382: Yes | F382: Yes
A383: 18009232732 | B383: 401K Sales - Ameritas | C383: External | D383: +18009232732 | E383: Yes | F383: Yes
A384: 18009812574 | B384: GRP_EBH | C384: IVR | D384: +18009812574 | E384: Yes | F384: Yes
A385: 18009924767 | B385: Family Services Life (Burial) | C385: External | D385: +18009924767 | E385: Yes | F385: Yes
A386: 18009924767B | B386: IM Claims - Burial Policies (M policies) | C386: External | D386: +18009924767 | E386: Yes | F386: Yes
A387: 18009995431 | B387: Vision Davis - Members | C387: External | D387: +18009995431 | E387: Yes | F387: Yes
A388: 18442223301 | B388: DI.com | C388: External | D388: +18442223301 | E388: Yes | F388: Yes
A389: 18444394846 | B389: Hey_Hugo | C389: IVR | D389: +18444394846 | E389: Yes | F389: Yes
A390: 18445615600 | B390: Dental Exchange Marketplace MEMBERS - opens 9 AM Eastern - Premier Access | C390: IVR | D390: +18445615600 | E390: Yes | F390: Yes
A391: 18445615600B | B391: DTC Exchange IVR | C391: IVR | D391: +18445615600 | E391: Yes | F391: Yes
A392: 18552146777 | B392: Avesis Toll Free | C392: External | D392: +18552146777 | E392: Yes | F392: Yes
A393: 18556290554 | B393: EAP - Guardian Employee - Option 3 for Employee Assistance Program - Spring Health - M-F 8 am-8 pm ET - Option 2 for CRISIS | C393: External | D393: +18556290554 | E393: Yes | F393: Yes
A394: 18556912341 | B394: MCM_All | C394: IVR | D394: +18556912341 | E394: Yes | F394: Yes
A395: 18557364542 | B395: Guardian Employee Pension | C395: External | D395: +18557364542 | E395: Yes | F395: Yes
A396: 18558862901 | B396: Transperfect | C396: External | D396: +18558862901 | E396: Yes | F396: Yes
A397: 18662291970 | B397: CRP_Recruitment | C397: IVR | D397: +18662291970 | E397: Yes | F397: Yes
...

Sheet Queues
A1: Built Prod | B1: Built Dev | C1: Queue Name | D1: Description | E1: Division | F1: Peer ID | G1: Outbound CID | H1: Outbound CID Name | I1: ACW Method | J1: ACW Timeout | K1: Scoring Method | L1: Routing Method | M1: Queue Evaluation Method | N1: BR1 EX | O1: BR1 TO | P1: BR1 Skills | Q1: BR1 SG | R1: BR1 MG | S1: Column6 | T1: Voice Alerting Timeout | U1: Voice Whisper Audio | V1: Voice SLA % (ex. 80) | W1: Voice SLA Target (20 seconds) | X1: Voice In Queue Flow | Y1: Script | Z1: Chat Alerting Timeout (30) | AA1: Chat Service Sevel % | AB1: Chat Service Level Target (20) | AC1: Chat Default Script | AD1: SMS Service Level % (80) | AE1: SMS Service Level Target (20) | AF1: Alerting Timeout (30) | AG1: SMS Default Script | AH1: SMS In-Queue Flow | AI1: Outbound SMS Number | AJ1: Email Service Level % | AK1: Email Service Level Target (86400) | AL1: Email Alerting Timeout (300) | AM1: Email Auto Answer | AN1: Outbound Email Address | AO1: In-queue Email Flow | AP1: Email Default Script | AQ1: Callback Service Level % (80) | AR1: Callback Service Level Target (20) | AS1: Callback Alerting Timeout (30) | AT1: Allow Agents to take ownership | AU1: Own Schedule Callback Time | AV1: Schedule Callback in Advance for | AW1: Voice Transcription | AX1: Manual Assignment | AY1: Advanced Routing | AZ1: Auto-Answer for all Digital Channels | BA1: Notes
C2: General_English | G2: 800 555-1234 | H2: Company Name | I2: Optional | K2: Conversation Score | M2: Disregard skills-next agent | N2: TIMEOUT_SECONDS | O2: 5 | P2: test 1 | Q2: test 1 = 1:Home | R2: bigTest1:none,bigTest2:none | T2: 8 | AX2: off | AZ2: off
G5: Information housed in separate spreadsheet - Mike W
C232: About contact center - Genesys Cloud Resource Center (mypurecloud.com)

Sheet BullseyeQueues
A1: Queue Name | B1: Description | C1: Division | D1: Peer ID | E1: Outbound CID | F1: Outbound CID Name | G1: ACW Method | H1: ACW Timeout | I1: Scoring Method | J1: Routing Method | K1: Queue Evaluation Method | L1: 1 BR EX | M1: 1 BR TO | N1: 1 BR Skills | O1: 1 BR SG | P1: 1 BR MG | Q1: 2 BR EX | R1: 2 BR TO | S1: 2 BR Skills | T1: 2 BR SG | U1: 2 BR MG | V1: 3 BR EX | W1: 3 BR TO | X1: 3 BR Skills | Y1: 3 BR SG | Z1: 3 BR MG | AA1: 4 BR EX | AB1: 4 BR TO | AC1: 4 BR Skills | AD1: 4 BR SG | AE1: 4 BR MG | AF1: 5 BR EX | AG1: 5 BR TO | AH1: 5 BR Skills | AI1: 5 BR SG | AJ1: 5 BR MG | AK1: 6 BR EX | AL1: 6 BR TO | AM1: 6 BR Skills | AN1: 6 BR SG | AO1: 6 BR MG | AP1: Voice Alerting Timeout | AQ1: Voice Whisper Audio | AR1: Voice SLA % (ex. 80) | AS1: Voice SLA Target (20 seconds) | AT1: Voice In Queue Flow | AU1: Script | AV1: Chat Alerting Timeout (30) | AW1: Chat Service Sevel % | AX1: Chat Service Level Target (20) | AY1: Chat Default Script | AZ1: SMS Service Level % (80) | BA1: SMS Service Level Target (20) | BB1: Alerting Timeout (30) | BC1: SMS Default Script | BD1: SMS In-Queue Flow | BE1: Outbound SMS Number | BF1: Email Service Level % | BG1: Email Service Level Target (86400) | BH1: Email Alerting Timeout (300) | BI1: Email Auto Answer | BJ1: Outbound Email Address | BK1: In-queue Email Flow | BL1: Email Default Script | BM1: Callback Service Level % (80) | BN1: Callback Service Level Target (20) | BO1: Callback Alerting Timeout (30) | BP1: Allow Agents to take ownership | BQ1: Own Schedule Callback Time | BR1: Schedule Callback in Advance for | BS1: Voice Transcription | BT1: Manual Assignment | BU1: Advanced Routing | BV1: Auto-Answer for all Digital Channels
A2: h4 | B2: ImportedQueue | C2: Home | E2: 8005551234 | F2: Company Name | G2: MANDATORY | I2: Conversation Score | K2: BEST | L2: TIMEOUT_SECONDS | M2: 5 | N2: test 1 | O2: test 1 = 1:Home | P2: bigTest1:none,bigTest2:none | Q2: TIMEOUT_SECONDS | R2: 5 | S2: test 2|test 3 | T2: test 1 = 2:Home | U2: bigTest3:none,bigTest4:none | V2: TIMEOUT_SECONDS | W2: 5 | X2: test 4 | Y2: test 1 = 3:Home | Z2: bigTest5:none,bigTest6:none | AP2: 8 | AR2: 80 | AS2: 20 | BT2: off | BV2: off
A3: h5 | B3: ImportedQueue | C3: Home | E3: 8005551234 | F3: Company Name | G3: OPTIONAL | I3: Conversation Score | K3: BEST | L3: TIMEOUT_SECONDS | M3: 5 | N3: test 1 | O3: test 1 = 1:Home | P3: bigTest1:none,bigTest2:none | Q3: TIMEOUT_SECONDS | R3: 5 | S3: test 2|test 3 | T3: test 1 = 2:Home | U3: bigTest3:none,bigTest4:none | V3: TIMEOUT_SECONDS | W3: 5 | X3: test 4 | Y3: test 1 = 3:Home | Z3: bigTest5:none,bigTest6:none | AP3: 8 | AR3: 80 | AS3: 20
A4: h6 | B4: ImportedQueue | C4: Home | E4: 8005551234 | F4: Company Name | G4: MANDATORY_TIMEOUT | H4: 5 | I4: Conversation Score | K4: ALL | L4: TIMEOUT_SECONDS | M4: 5 | N4: test 1 | O4: test 1 = 1:Home | P4: bigTest1:none,bigTest2:none | Q4: TIMEOUT_SECONDS | R4: 5 | S4: test 2|test 3 | T4: test 1 = 2:Home | U4: bigTest3:none,bigTest4:none | V4: TIMEOUT_SECONDS | W4: 5 | X4: test 4 | Y4: test 1 = 3:Home | Z4: bigTest5:none,bigTest6:none | AP4: 8 | AR4: 80 | AS4: 20

Sheet BullseyeQueuesCSV
A1: queue | B1: division | C1: acw | D1: inQueueFlow | E1: routingRules | F1: callScript | G1: groupRouting | H1: bullseye | I1: MemberGroups | J1: evaluation | K1: callerIDNum | L1: callerIDName | M1: alerting_timeout_seconds | N1: slPercentage | O1: slDuration_ms
A2: =BullseyeQueues!A2 -> h4 | B2: =BullseyeQueues!C2 -> Home | C2: =_xlfn.CONCAT(BullseyeQueues!G2,IF(OR(BullseyeQueues!G2="MANDATORY",BullseyeQueues!G2="OPTIONAL"),"",_xlfn.CONCAT(":",BullseyeQueues!H2))) -> MANDATORY | D2: =IF(ISBLANK(BullseyeQueues!AT2),"Default In-Queue Flow",BullseyeQueues!AT2) -> Default In-Queue Flow | F2: =IF(ISBLANK(BullseyeQueues!AU2),"",BullseyeQueues!AU2) | H2: =IF(ISBLANK(BullseyeQueues!L2),"",_xlfn.CONCAT(BullseyeQueues!L2,":",BullseyeQueues!M2,":",BullseyeQueues!N2,IF(ISBLANK(BullseyeQueues!Q2),"",_xlfn.CONCAT(",",BullseyeQueues!Q2,":",BullseyeQueues!R2,":",BullseyeQueues!S2,IF(ISBLANK(BullseyeQueues!V2),"",_xlfn.CONCAT(",",BullseyeQueues!V2,":",BullseyeQueues!W2,":",BullseyeQueues!X2,IF(ISBLANK(BullseyeQueues!AA2),"",_xlfn.CONCAT(",",BullseyeQueues!AA2,":",BullseyeQueues!AB2,":",BullseyeQueues!AC2,IF(ISBLANK(BullseyeQueues!AF2),"",_xlfn.CONCAT(",",BullseyeQueues!AF2,":",BullseyeQueues!AG2,":",BullseyeQueues!AH2,IF(ISBLANK(BullseyeQueues!AK2),"",_xlfn.CONCAT(",",BullseyeQueues!AK2,":",BullseyeQueues!AL2,":",BullseyeQueues!AM2)))))))))))) -> TIMEOUT_SECONDS:5:test 1,TIMEOUT_SECONDS:5:test 2|test 3,TIMEOUT_SECONDS:5:test 4 | I2: =_xlfn.CONCAT(IF(ISBLANK(BullseyeQueues!$O2),"",BullseyeQueues!$O2),IF(ISBLANK(BullseyeQueues!$P2),"",IF(ISBLANK(BullseyeQueues!$O2),BullseyeQueues!$P2,_xlfn.CONCAT(",",BullseyeQueues!$P2))),"|",IF(ISBLANK(BullseyeQueues!T2),"",BullseyeQueues!T2),IF(ISBLANK(BullseyeQueues!U2),"",IF(ISBLANK(BullseyeQueues!T2),BullseyeQueues!U2,_xlfn.CONCAT(",",BullseyeQueues!U2))),"|",IF(ISBLANK(BullseyeQueues!Y2),"",BullseyeQueues!Y2),IF(ISBLANK(BullseyeQueues!Z2),"",IF(ISBLANK(BullseyeQueues!Y2),BullseyeQueues!Z2,_xlfn.CONCAT(",",BullseyeQueues!Z2))),"|",IF(ISBLANK(BullseyeQueues!AD2),"",BullseyeQueues!AD2),IF(ISBLANK(BullseyeQueues!AE2),"",IF(ISBLANK(BullseyeQueues!AD2),BullseyeQueues!AE2,_xlfn.CONCAT(",",BullseyeQueues!AE2))),"|",IF(ISBLANK(BullseyeQueues!AI2),"",BullseyeQueues!AI2),IF(ISBLANK(BullseyeQueues!AJ2),"",IF(ISBLANK(BullseyeQueues!AI2),BullseyeQueues!AJ2,_xlfn.CONCAT(",",BullseyeQueues!AJ2))),"|",IF(ISBLANK(BullseyeQueues!AN2),"",BullseyeQueues!AN2),IF(ISBLANK(BullseyeQueues!AO2),"",IF(ISBLANK(BullseyeQueues!AN2),BullseyeQueues!AO2,_xlfn.CONCAT(",",BullseyeQueues!AO2)))) -> test 1 = 1:Home,bigTest1:none,bigTest2:none|test 1 = 2:Home,bigTest3:none,bigTest4:none|test 1 = 3:Home,bigTest5:none,bigTest6:none||| | J2: =BullseyeQueues!K2 -> BEST | K2: =BullseyeQueues!E2 -> 8005551234 | L2: =BullseyeQueues!F2 -> Company Name | M2: =BullseyeQueues!AP2 -> 8 | N2: =BullseyeQueues!AR2/100 -> 0.8 | O2: =BullseyeQueues!AS2*1000 -> 20000
A3: =BullseyeQueues!A3 -> h5 | B3: =BullseyeQueues!C3 -> Home | C3: =_xlfn.CONCAT(BullseyeQueues!G3,IF(OR(BullseyeQueues!G3="MANDATORY",BullseyeQueues!G3="OPTIONAL"),"",_xlfn.CONCAT(":",BullseyeQueues!H3))) -> OPTIONAL | D3: =IF(ISBLANK(BullseyeQueues!AT3),"Default In-Queue Flow",BullseyeQueues!AT3) -> Default In-Queue Flow | F3: =IF(ISBLANK(BullseyeQueues!AU3),"",BullseyeQueues!AU3) | H3: =IF(ISBLANK(BullseyeQueues!L3),"",_xlfn.CONCAT(BullseyeQueues!L3,":",BullseyeQueues!M3,":",BullseyeQueues!N3,IF(ISBLANK(BullseyeQueues!Q3),"",_xlfn.CONCAT(",",BullseyeQueues!Q3,":",BullseyeQueues!R3,":",BullseyeQueues!S3,IF(ISBLANK(BullseyeQueues!V3),"",_xlfn.CONCAT(",",BullseyeQueues!V3,":",BullseyeQueues!W3,":",BullseyeQueues!X3,IF(ISBLANK(BullseyeQueues!AA3),"",_xlfn.CONCAT(",",BullseyeQueues!AA3,":",BullseyeQueues!AB3,":",BullseyeQueues!AC3,IF(ISBLANK(BullseyeQueues!AF3),"",_xlfn.CONCAT(",",BullseyeQueues!AF3,":",BullseyeQueues!AG3,":",BullseyeQueues!AH3,IF(ISBLANK(BullseyeQueues!AK3),"",_xlfn.CONCAT(",",BullseyeQueues!AK3,":",BullseyeQueues!AL3,":",BullseyeQueues!AM3)))))))))))) -> TIMEOUT_SECONDS:5:test 1,TIMEOUT_SECONDS:5:test 2|test 3,TIMEOUT_SECONDS:5:test 4 | I3: =_xlfn.CONCAT(IF(ISBLANK(BullseyeQueues!$O3),"",BullseyeQueues!$O3),IF(ISBLANK(BullseyeQueues!$P3),"",IF(ISBLANK(BullseyeQueues!$O3),BullseyeQueues!$P3,_xlfn.CONCAT(",",BullseyeQueues!$P3))),"|",IF(ISBLANK(BullseyeQueues!T3),"",BullseyeQueues!T3),IF(ISBLANK(BullseyeQueues!U3),"",IF(ISBLANK(BullseyeQueues!T3),BullseyeQueues!U3,_xlfn.CONCAT(",",BullseyeQueues!U3))),"|",IF(ISBLANK(BullseyeQueues!Y3),"",BullseyeQueues!Y3),IF(ISBLANK(BullseyeQueues!Z3),"",IF(ISBLANK(BullseyeQueues!Y3),BullseyeQueues!Z3,_xlfn.CONCAT(",",BullseyeQueues!Z3))),"|",IF(ISBLANK(BullseyeQueues!AD3),"",BullseyeQueues!AD3),IF(ISBLANK(BullseyeQueues!AE3),"",IF(ISBLANK(BullseyeQueues!AD3),BullseyeQueues!AE3,_xlfn.CONCAT(",",BullseyeQueues!AE3))),"|",IF(ISBLANK(BullseyeQueues!AI3),"",BullseyeQueues!AI3),IF(ISBLANK(BullseyeQueues!AJ3),"",IF(ISBLANK(BullseyeQueues!AI3),BullseyeQueues!AJ3,_xlfn.CONCAT(",",BullseyeQueues!AJ3))),"|",IF(ISBLANK(BullseyeQueues!AN3),"",BullseyeQueues!AN3),IF(ISBLANK(BullseyeQueues!AO3),"",IF(ISBLANK(BullseyeQueues!AN3),BullseyeQueues!AO3,_xlfn.CONCAT(",",BullseyeQueues!AO3)))) -> test 1 = 1:Home,bigTest1:none,bigTest2:none|test 1 = 2:Home,bigTest3:none,bigTest4:none|test 1 = 3:Home,bigTest5:none,bigTest6:none||| | J3: =BullseyeQueues!K3 -> BEST | K3: =BullseyeQueues!E3 -> 8005551234 | L3: =BullseyeQueues!F3 -> Company Name | M3: =BullseyeQueues!AP3 -> 8 | N3: =BullseyeQueues!AR3/100 -> 0.8 | O3: =BullseyeQueues!AS3*1000 -> 20000
A4: =BullseyeQueues!A4 -> h6 | B4: =BullseyeQueues!C4 -> Home | C4: =_xlfn.CONCAT(BullseyeQueues!G4,IF(OR(BullseyeQueues!G4="MANDATORY",BullseyeQueues!G4="OPTIONAL"),"",_xlfn.CONCAT(":",BullseyeQueues!H4))) -> MANDATORY_TIMEOUT:5 | D4: =IF(ISBLANK(BullseyeQueues!AT4),"Default In-Queue Flow",BullseyeQueues!AT4) -> Default In-Queue Flow | F4: =IF(ISBLANK(BullseyeQueues!AU4),"",BullseyeQueues!AU4) | H4: =IF(ISBLANK(BullseyeQueues!L4),"",_xlfn.CONCAT(BullseyeQueues!L4,":",BullseyeQueues!M4,":",BullseyeQueues!N4,IF(ISBLANK(BullseyeQueues!Q4),"",_xlfn.CONCAT(",",BullseyeQueues!Q4,":",BullseyeQueues!R4,":",BullseyeQueues!S4,IF(ISBLANK(BullseyeQueues!V4),"",_xlfn.CONCAT(",",BullseyeQueues!V4,":",BullseyeQueues!W4,":",BullseyeQueues!X4,IF(ISBLANK(BullseyeQueues!AA4),"",_xlfn.CONCAT(",",BullseyeQueues!AA4,":",BullseyeQueues!AB4,":",BullseyeQueues!AC4,IF(ISBLANK(BullseyeQueues!AF4),"",_xlfn.CONCAT(",",BullseyeQueues!AF4,":",BullseyeQueues!AG4,":",BullseyeQueues!AH4,IF(ISBLANK(BullseyeQueues!AK4),"",_xlfn.CONCAT(",",BullseyeQueues!AK4,":",BullseyeQueues!AL4,":",BullseyeQueues!AM4)))))))))))) -> TIMEOUT_SECONDS:5:test 1,TIMEOUT_SECONDS:5:test 2|test 3,TIMEOUT_SECONDS:5:test 4 | I4: =_xlfn.CONCAT(IF(ISBLANK(BullseyeQueues!$O4),"",BullseyeQueues!$O4),IF(ISBLANK(BullseyeQueues!$P4),"",IF(ISBLANK(BullseyeQueues!$O4),BullseyeQueues!$P4,_xlfn.CONCAT(",",BullseyeQueues!$P4))),"|",IF(ISBLANK(BullseyeQueues!T4),"",BullseyeQueues!T4),IF(ISBLANK(BullseyeQueues!U4),"",IF(ISBLANK(BullseyeQueues!T4),BullseyeQueues!U4,_xlfn.CONCAT(",",BullseyeQueues!U4))),"|",IF(ISBLANK(BullseyeQueues!Y4),"",BullseyeQueues!Y4),IF(ISBLANK(BullseyeQueues!Z4),"",IF(ISBLANK(BullseyeQueues!Y4),BullseyeQueues!Z4,_xlfn.CONCAT(",",BullseyeQueues!Z4))),"|",IF(ISBLANK(BullseyeQueues!AD4),"",BullseyeQueues!AD4),IF(ISBLANK(BullseyeQueues!AE4),"",IF(ISBLANK(BullseyeQueues!AD4),BullseyeQueues!AE4,_xlfn.CONCAT(",",BullseyeQueues!AE4))),"|",IF(ISBLANK(BullseyeQueues!AI4),"",BullseyeQueues!AI4),IF(ISBLANK(BullseyeQueues!AJ4),"",IF(ISBLANK(BullseyeQueues!AI4),BullseyeQueues!AJ4,_xlfn.CONCAT(",",BullseyeQueues!AJ4))),"|",IF(ISBLANK(BullseyeQueues!AN4),"",BullseyeQueues!AN4),IF(ISBLANK(BullseyeQueues!AO4),"",IF(ISBLANK(BullseyeQueues!AN4),BullseyeQueues!AO4,_xlfn.CONCAT(",",BullseyeQueues!AO4)))) -> test 1 = 1:Home,bigTest1:none,bigTest2:none|test 1 = 2:Home,bigTest3:none,bigTest4:none|test 1 = 3:Home,bigTest5:none,bigTest6:none||| | J4: =BullseyeQueues!K4 -> ALL | K4: =BullseyeQueues!E4 -> 8005551234 | L4: =BullseyeQueues!F4 -> Company Name | M4: =BullseyeQueues!AP4 -> 8 | N4: =BullseyeQueues!AR4/100 -> 0.8 | O4: =BullseyeQueues!AS4*1000 -> 20000

Sheet CGRQueues
A1: Queue Name | B1: Description | C1: Division | D1: Peer ID | E1: Outbound CID | F1: Outbound CID Name | G1: ACW Method | H1: ACW Timeout | I1: Scoring Method | J1: Routing Method | K1: Queue Evaluation Method | L1: 1 CGR Metric | M1: 1 CGR Operator | N1: 1 CGR Value | O1: 1 CGR Wait Sec. | P1: 1 CGR SG | Q1: 1 CGR MG | R1: 2 CGR Metric | S1: 2 CGR Operator | T1: 2 CGR Value | U1: 2 CGR Wait Sec. | V1: 2 CGR SG | W1: 2 CGR MG | X1: 3 CGR Metric | Y1: 3 CGR Operator | Z1: 3 CGR Value | AA1: 3 CGR Wait Sec. | AB1: 3 CGR SG | AC1: 3 CGR MG | AD1: 4 CGR Metric | AE1: 4 CGR Operator | AF1: 4 CGR Value | AG1: 4 CGR Wait Sec. | AH1: 4 CGR SG | AI1: 4 CGR MG | AJ1: 5 CGR Metric | AK1: 5 CGR Operator | AL1: 5 CGR Value | AM1: 5 CGR Wait Sec. | AN1: 5 CGR SG | AO1: 5 CGR MG | AP1: 6 CGR Metric | AQ1: 6 CGR Operator | AR1: 6 CGR Value | AS1: 6 CGR Wait Sec. | AT1: 6 CGR SG | AU1: 6 CGR MG | AV1: Voice Alerting Timeout | AW1: Voice Whisper Audio | AX1: Voice SLA % (ex. 80) | AY1: Voice SLA Target (20 seconds) | AZ1: Voice In Queue Flow | BA1: Script | BB1: Chat Alerting Timeout (30) | BC1: Chat Service Sevel % | BD1: Chat Service Level Target (20) | BE1: Chat Default Script | BF1: SMS Service Level % (80) | BG1: SMS Service Level Target (20) | BH1: Alerting Timeout (30) | BI1: SMS Default Script | BJ1: SMS In-Queue Flow | BK1: Outbound SMS Number | BL1: Email Service Level % | BM1: Email Service Level Target (86400) | BN1: Email Alerting Timeout (300) | BO1: Email Auto Answer | BP1: Outbound Email Address | BQ1: In-queue Email Flow | BR1: Email Default Script | BS1: Callback Service Level % (80) | BT1: Callback Service Level Target (20) | BU1: Callback Alerting Timeout (30) | BV1: Allow Agents to take ownership | BW1: Own Schedule Callback Time | BX1: Schedule Callback in Advance for | BY1: Voice Transcription | BZ1: Manual Assignment | CA1: Advanced Routing | CB1: Auto-Answer for all Digital Channels
A2: h1 | B2: ImportedQueue | C2: Home | E2: 800 555-1234 | F2: Company Name | G2: MANDATORY | I2: Conversation Score | K2: BEST | L2: EstimatedWaitTime | M2: GreaterThan | N2: 30 | O2: 2 | P2: test 1 = 1:Home | Q2: bigTest1:none,bigTest2:none | R2: EstimatedWaitTime | S2: GreaterThan | T2: 30 | U2: 2 | V2: test 1 = 1:Home | W2: bigTest1:none,bigTest2:none | X2: EstimatedWaitTime | Y2: GreaterThan | Z2: 30 | AA2: 2 | AB2: test 1 = 1:Home | AC2: bigTest1:none,bigTest2:none | AD2: EstimatedWaitTime | AE2: GreaterThan | AF2: 30 | AG2: 2 | AH2: test 1 = 1:Home | AI2: bigTest1:none,bigTest2:none | AJ2: EstimatedWaitTime | AK2: GreaterThan | AL2: 30 | AM2: 2 | AN2: test 1 = 1:Home | AO2: bigTest1:none,bigTest2:none | AP2: EstimatedWaitTime | AQ2: GreaterThan | AR2: 30 | AS2: 2 | AT2: test 1 = 1:Home | AU2: bigTest1:none,bigTest2:none | AV2: 8 | AX2: 80 | AY2: 20 | BZ2: off | CB2: off
A3: h2 | B3: ImportedQueue | C3: Home | E3: 801 555-1234 | F3: Company Name | G3: OPTIONAL | I3: Conversation Score | K3: BEST | L3: EstimatedWaitTime | M3: GreaterThan | N3: 30 | O3: 2 | P3: test 1 = 1:Home | Q3: bigTest1:none,bigTest2:none | R3: EstimatedWaitTime | S3: GreaterThan | T3: 30 | U3: 2 | V3: test 1 = 1:Home | W3: bigTest1:none,bigTest2:none | X3: EstimatedWaitTime | Y3: GreaterThan | Z3: 30 | AA3: 2 | AB3: test 1 = 1:Home | AC3: bigTest1:none,bigTest2:none | AD3: EstimatedWaitTime | AE3: GreaterThan | AF3: 30 | AG3: 2 | AH3: test 1 = 1:Home | AI3: bigTest1:none,bigTest2:none | AJ3: EstimatedWaitTime | AK3: GreaterThan | AL3: 30 | AM3: 2 | AN3: test 1 = 1:Home | AO3: bigTest1:none,bigTest2:none | AP3: EstimatedWaitTime | AQ3: GreaterThan | AR3: 30 | AS3: 2 | AT3: test 1 = 1:Home | AU3: bigTest1:none,bigTest2:none | AV3: 8 | AX3: 80 | AY3: 20
A4: h3 | B4: ImportedQueue | C4: Home | E4: 802 555-1234 | F4: Company Name | G4: MANDATORY_TIMEOUT | H4: 5 | I4: Conversation Score | K4: ALL | L4: EstimatedWaitTime | M4: GreaterThan | N4: 30 | O4: 2 | P4: test 1 = 1:Home | Q4: bigTest1:none,bigTest2:none | R4: EstimatedWaitTime | S4: GreaterThan | T4: 30 | U4: 2 | V4: test 1 = 1:Home | W4: bigTest1:none,bigTest2:none | X4: EstimatedWaitTime | Y4: GreaterThan | Z4: 30 | AA4: 2 | AB4: test 1 = 1:Home | AC4: bigTest1:none,bigTest2:none | AD4: EstimatedWaitTime | AE4: GreaterThan | AF4: 30 | AG4: 2 | AH4: test 1 = 1:Home | AI4: bigTest1:none,bigTest2:none | AJ4: EstimatedWaitTime | AK4: GreaterThan | AL4: 30 | AM4: 2 | AN4: test 1 = 1:Home | AO4: bigTest1:none,bigTest2:none | AP4: EstimatedWaitTime | AQ4: GreaterThan | AR4: 30 | AS4: 2 | AT4: test 1 = 1:Home | AU4: bigTest1:none,bigTest2:none | AV4: 8 | AX4: 80 | AY4: 20
A5: h4 | B5: ImportedQueue | C5: Home | E5: 803 555-1234 | F5: Company Name | G5: MANDATORY_FORCED_TIMEOUT | H5: 5 | I5: Conversation Score | K5: NONE | L5: EstimatedWaitTime | M5: GreaterThan | N5: 30 | O5: 2 | P5: test 1 = 1:Home | Q5: bigTest1:none,bigTest2:none | R5: EstimatedWaitTime | S5: GreaterThan | T5: 30 | U5: 2 | V5: test 1 = 1:Home | W5: bigTest1:none,bigTest2:none | X5: EstimatedWaitTime | Y5: GreaterThan | Z5: 30 | AA5: 2 | AB5: test 1 = 1:Home | AC5: bigTest1:none,bigTest2:none | AD5: EstimatedWaitTime | AE5: GreaterThan | AF5: 30 | AG5: 2 | AH5: test 1 = 1:Home | AI5: bigTest1:none,bigTest2:none | AJ5: EstimatedWaitTime | AK5: GreaterThan | AL5: 30 | AM5: 2 | AN5: test 1 = 1:Home | AO5: bigTest1:none,bigTest2:none | AP5: EstimatedWaitTime | AQ5: GreaterThan | AR5: 30 | AS5: 2 | AT5: test 1 = 1:Home | AU5: bigTest1:none,bigTest2:none | AV5: 8 | AX5: 80 | AY5: 20
A6: h5 | B6: ImportedQueue | C6: Home | E6: 804 555-1234 | F6: Company Name | G6: AGENT_REQUESTED | H6: 5 | I6: Conversation Score | K6: NONE | L6: EstimatedWaitTime | M6: GreaterThan | N6: 30 | O6: 2 | P6: test 1 = 1:Home | Q6: bigTest1:none,bigTest2:none | R6: EstimatedWaitTime | S6: GreaterThan | T6: 30 | U6: 2 | V6: test 1 = 1:Home | W6: bigTest1:none,bigTest2:none | X6: EstimatedWaitTime | Y6: GreaterThan | Z6: 30 | AA6: 2 | AB6: test 1 = 1:Home | AC6: bigTest1:none,bigTest2:none | AD6: EstimatedWaitTime | AE6: GreaterThan | AF6: 30 | AG6: 2 | AH6: test 1 = 1:Home | AI6: bigTest1:none,bigTest2:none | AJ6: EstimatedWaitTime | AK6: GreaterThan | AL6: 30 | AM6: 2 | AN6: test 1 = 1:Home | AO6: bigTest1:none,bigTest2:none | AP6: EstimatedWaitTime | AQ6: GreaterThan | AR6: 30 | AS6: 2 | AT6: test 1 = 1:Home | AU6: bigTest1:none,bigTest2:none | AV6: 8 | AX6: 80 | AY6: 20

Sheet Wrap-Up Codes
A1: Wrap-Up Codes | B1: About wrap-up codes - Genesys Cloud Resource Center (mypurecloud.com)
A2: Wrap-Up Code | B2: Assocaited Queue(s) | C2: Division | D2: Built Prod | E2: Built Dev
D3: No | E3: No

Sheet Canned Responses
A1: Canned Responses | B1: About canned responses - Genesys Cloud Resource Center (mypurecloud.com)
A2: Libraries
A3: Library 1
A8: Response | B8: Library | C8: Type | D8: Content
A9: Response 1 | B9: Library 1 | C9: Standard | D9: Thank you for contacting us. My name is {{AGENT_NAME}}.

Sheet Prompts
A1: Name | B1: Type | C1: Description | D1: tts_en-us | E1: audio_en-us | F1: tts_es-us | G1: audio_es-us
A2: MainMenuOptions | B2: User | D2: For xxx, press 1. To speak to an agent, press 2. | E2: ENG_promptName.wav | F2: Spanish Verbiage | G2: SPA_PromptName.wav

Sheet Email Domains
A1: Email Configuration
A2: Genesys Cloud Domain | B2: About ACD emails - Genesys Cloud Resource Center (mypurecloud.com)
A3: support@pure.cloud | B3: Email routing scenarios - Genesys Cloud Resource Center (mypurecloud.com)
A4: domain2@pure.cloud
A6: Custom Domain Name | B6: About the custom SMTP server integration for outbound emails - Genesys Cloud Resource Center (mypurecloud.com)
A7: company.com
A8: Type | E8: Custom
A9: Domain Settings | B9: CUSTOM CONFIGURATION | C9: Domain Verification Add this verification record to your domain's DNS settings to verify ownership of your domain. Verifying the domain will allow Genesys Cloud to send outbound emails from this domain. Please note this verification process may take up to 72 hours. | D9: Name
D10: Type | E10: TXT
D11: Value | E11: <to be retrieved on the Org>
C12: MX Record for Inbound Email Add this MX record to your domain's DNS Settings. All email sent to this domain will route directly to Genesys Cloud. Please note this verification process may take up to 72 hours. Be sure not to use a domain that's already being used for email within your organization. | D12: Name
D13: Type | E13: MX
D14: Value | E14: <to be retrieved on the Org>
B15: CUSTOM CONFIGURATION / Advanced Settings | C15: DKIM Authentication While not required, DKIM authentication is recommended to prevent outbound email from being marked as spam. Add these CNAME records to your DNS settings. Once Genesys Cloud has verified these records, outbound emails will start using DKIM. | D15: Name | E15: UNIQUE_TOKEN_1._domainkey.support.company.com UNIQUE_TOKEN_2._domainkey.support.company.com UNIQUE_TOKEN_3._domainkey.support.company.com
D16: Type | E16: CNAME
D17: Value | E17: <to be retrieved on the Org> UNIQUE_TOKEN_1.dkim.amazonses.com UNIQUE_TOKEN_2.dkim.amazonses.com UNIQUE_TOKEN_3.dkim.amazonses.com
C18: SPF DMARC Authentication (Custom MAIL FROM) By default, Genesys Cloud will use amazonses.com as the MAIL FROM value on your email domain. This will allow the SPF check to automatically pass as the mail is sent from amazonses.com. If you wish to use a custom MAIL FROM domain, specify it in the field below. You will then be presented with some additional DNS records that you will need to add to complete the verification. Please note the MAIL FROM value must be a subdomain of your email domain. | E18: <Set custom MAIL FROM domain>
B19: OUTBOUND EMAIL SENDING | C19: Use my organization's SMTP server for sending outbound emails Note: SMTP server settings are configured in | E19: NO
C20: Custom SMTP Server

Sheet Email Addresses
A1: Email Address Configuration | E1: Email routing scenarios - Genesys Cloud Resource Center (mypurecloud.com)
A2: Email Address 1 | D2: support@company.com
A3: From Name Name that appears to the recipient when an agent responds to an email. | D3: EMEA Services Company
A4: From Email Address Specify an email address that appears to the recipient when an agent responds to an email. This address must be configured in Genesys Cloud; previous Bcc and Reply To settings will be carried over with the specified email address. | D4: global@services.company.mypurecloud.ie
A5: Reply To This address overrides the "Reply to" address the customer sees when replying to the original email. If you forward email to Genesys Cloud and want to exclude the forwarding address from replies, set the forwarding address as the Reply To. | D5: Override Reply To address used: global@services.company.mypurecloud.ie <Automatically set and not changeable if value for "From Email Address" is set>
A6: BCC Recipients The specified recipients will be automatically added to the BCC list for outbound emails and cannot be removed by agents. | D6: <none>
A7: Email Routing All email, except spam, will follow the specified route option. | B7: Always Route to this flow | D7: n/a
B8: Always Route to this queue | C8: Queue | D8: EMEA Services
C9: Skills | D9: <none>
C10: Language | D10: <none>
C11: Priority | D11: 0
B12: Do not route (outbound email only) | D12: n/a
A13: Spam Routing The system determines spam as potentially harmful emails. Specify an option for spam email. | B13: Route spam email to this flow | D13: n/a
B14: Disconnect all email that is detected as spam | D14: YES

Sheet QM Evaluation Form
A1: Quality Evaluation Forms | C1: About quality management - Genesys Cloud Resource Center (mypurecloud.com)
C2: Create and publish an evaluation form - Genesys Cloud Resource Center (mypurecloud.com)
A3: Evaluation Form Name | B3: Eval Form 1
A4: Question group 1 Name | B4: Weight | C4: N/A Enabled? | D4: Default to Highest Scoring / NA?
A5: Group 1 name | B5: 1 | C5: No | D5: No
A6: Question text | B6: Question type | C6: Value (list in order and separate by comma) | D6: N/A Enabled | E6: Conditional Quesiton | F6: Conditional Information | G6: Comments Required | H6: Critical Question | I6: Fatal Quesiton
A7: Agent followed procedure xx | B7: Yes/No | C7: 1,0
A12: Question group 2 Name | B12: Weight | C12: N/A Enabled? | D12: Default to Highest Scoring / NA?
A13: Group 2 name | B13: 2 | C13: Yes | D13: No
A14: Question text | B14: Question type | C14: Value (list in order and separate by comma) | D14: N/A Enabled | E14: Conditional Quesiton | F14: Conditional Information | G14: Comments Required | H14: Critical Question | I14: Fatal Quesiton

Sheet Workbook Versioning
A1: Version | B1: Created On | C1: Created/Updated By | D1: Version Update Overview
A2: 0.01
